Workbook

Sheet Summary
A1: BSTI 2.0 – Revised financial structure (work-volume based, ≤ 2 crore per approval)
A2: Prepared 19 Oct 2026. Basis: OrangeBD Financial Proposal V4 (Sep 2026), BSTI 2.0.pptx feature counts, BSTI priority list (serial.docx). Rollout total unchanged; amounts exclude VAT unless stated.
B4: Rollout total (unchanged) | C4: =Inputs!B4 -> 111665000
B5: Maintenance 2030–31 (unchanged) | C5: =Inputs!B10 -> 75240000
B6: Grand total (excl. VAT) | C6: =C4+C5 -> 186905000
B7: Number of approval packages (rollout) | C7: =COUNTA(Packages!A5:A12) -> 8
B8: Largest approval incl. VAT (crore) | C8: =Packages!F16 -> 1.997205
B9: Last go-live deadline | C9: =Packages!U13 -> 47483
A11: Approval packages
A12: Package | B12: Scope | C12: Value (BDT, excl. VAT) | D12: Value incl. VAT (BDT) | E12: Crore incl. VAT | F12: Cap check | G12: Work start | H12: Go-live deadline
A13: =Packages!A5 -> WP0 | B13: =Packages!B5 -> Interim operation & maintenance of the 5 live services (Aug–Dec 2026), as proposed | C13: =Packages!F5 -> 1625000 | D13: =Packages!H5 -> 1868750 | E13: =Packages!I5 -> 0.186875 | F13: =Packages!J5 -> OK | G13: =Packages!K5 -> 46235 | H13: =Packages!U5 -> 46387
A14: =Packages!A6 -> WP1 | B14: =Packages!B6 -> BSTI 2.0 transformation: common platform, HRM & Leave, Payroll, Standards (BDS) sale; Accounts | C14: =Packages!F6 -> 12379000 | D14: =Packages!H6 -> 14235850 | E14: =Packages!I6 -> 1.423585 | F14: =Packages!J6 -> OK | G14: =Packages!K6 -> 46388 | H14: =Packages!U6 -> 46568
A15: =Packages!A7 -> WP2 | B15: =Packages!B7 -> CM licence services (non-scope & scope: new, renewal, brand inclusion) + common suspension / cancellation / withdrawal | C15: =Packages!F7 -> 16120000 | D15: =Packages!H7 -> 18538000 | E15: =Packages!I7 -> 1.8538 | F15: =Packages!J7 -> OK | G15: =Packages!K7 -> 46447 | H15: =Packages!U7 -> 46721
A16: =Packages!A8 -> WP3 | B16: =Packages!B8 -> Laboratory testing (Chemical, Physical, Energy Meter) and PCR services | C16: =Packages!F8 -> 17063000 | D16: =Packages!H8 -> 19622450 | E16: =Packages!I8 -> 1.962245 | F16: =Packages!J8 -> OK | G16: =Packages!K8 -> 46419 | H16: =Packages!U8 -> 46721
A17: =Packages!A9 -> WP4 | B17: =Packages!B9 -> Enforcement & field metrology: Mobile Court, Surveillance, Verification, Tank Calibration, Metrology Licence, Storage Tank Calibration | C17: =Packages!F9 -> 17336000 | D17: =Packages!H9 -> 19936400 | E17: =Packages!I9 -> 1.99364 | F17: =Packages!J9 -> OK | G17: =Packages!K9 -> 46844 | H17: =Packages!U9 -> 47118
A18: =Packages!A10 -> WP5 | B18: =Packages!B10 -> MSC services (issue, renewal, scope inclusion) | C18: =Packages!F10 -> 16241000 | D18: =Packages!H10 -> 18677150 | E18: =Packages!I10 -> 1.867715 | F18: =Packages!J10 -> OK | G18: =Packages!K10 -> 47027 | H18: =Packages!U10 -> 47299
A19: =Packages!A11 -> WP6 | B19: =Packages!B11 -> Halal certification, LPG / Fuel station registration, Case Management | C19: =Packages!F11 -> 17367000 | D19: =Packages!H11 -> 19972050 | E19: =Packages!I11 -> 1.997205 | F19: =Packages!J11 -> OK | G19: =Packages!K11 -> 47119 | H19: =Packages!U11 -> 47391
A20: =Packages!A12 -> WP7 | B20: =Packages!B12 -> I&S Metrology Calibration (NML), Building measurement, BSW API integration, Importer/Exporter certificates* | C20: =Packages!F12 -> 13534000 | D20: =Packages!H12 -> 15564100 | E20: =Packages!I12 -> 1.55641 | F20: =Packages!J12 -> OK | G20: =Packages!K12 -> 47209 | H20: =Packages!U12 -> 47483
B21: TOTAL ROLLOUT | C21: =SUM(C13:C20) -> 111665000 | D21: =SUM(D13:D20) -> 128414750 | E21: =SUM(E13:E20) -> 12.841475
A25: Year-wise cash flow: revised vs proposal (BDT, excl. VAT)
A26: Year | C26: Proposal (as submitted) | D26: Revised: rollout | E26: Revised: maintenance | F26: Revised: total | G26: Difference, revised − proposal (lakh) | H26: Revised incl. VAT
A27: 2026 | C27: =SUMIF('Original Offer'!$B$5:$B$19,VALUE(A27),'Original Offer'!$F$5:$F$19) -> 1625000 | D27: =SUMIFS('Payment Schedule'!$G$5:$G$41,'Payment Schedule'!$F$5:$F$41,VALUE(A27),'Payment Schedule'!$A$5:$A$41,"Rollout") -> 1625000 | E27: =SUMIFS('Payment Schedule'!$G$5:$G$41,'Payment Schedule'!$F$5:$F$41,VALUE(A27),'Payment Schedule'!$A$5:$A$41,"Maintenance") -> 0 | F27: =D27+E27 -> 1625000 | G27: =(F27-C27)/100000 -> 0 | H27: =SUMIF('Payment Schedule'!$F$5:$F$41,VALUE(A27),'Payment Schedule'!$I$5:$I$41) -> 1868750
A28: 2027 | C28: =SUMIF('Original Offer'!$B$5:$B$19,VALUE(A28),'Original Offer'!$F$5:$F$19) -> 20520000 | D28: =SUMIFS('Payment Schedule'!$G$5:$G$41,'Payment Schedule'!$F$5:$F$41,VALUE(A28),'Payment Schedule'!$A$5:$A$41,"Rollout") -> 42243700 | E28: =SUMIFS('Payment Schedule'!$G$5:$G$41,'Payment Schedule'!$F$5:$F$41,VALUE(A28),'Payment Schedule'!$A$5:$A$41,"Maintenance") -> 0 | F28: =D28+E28 -> 42243700 | G28: =(F28-C28)/100000 -> 217.237 | H28: =SUMIF('Payment Schedule'!$F$5:$F$41,VALUE(A28),'Payment Schedule'!$I$5:$I$41) -> 48580255
A29: 2028 | C29: =SUMIF('Original Offer'!$B$5:$B$19,VALUE(A29),'Original Offer'!$F$5:$F$19) -> 39990000 | D29: =SUMIFS('Payment Schedule'!$G$5:$G$41,'Payment Schedule'!$F$5:$F$41,VALUE(A29),'Payment Schedule'!$A$5:$A$41,"Rollout") -> 22168900 | E29: =SUMIFS('Payment Schedule'!$G$5:$G$41,'Payment Schedule'!$F$5:$F$41,VALUE(A29),'Payment Schedule'!$A$5:$A$41,"Maintenance") -> 0 | F29: =D29+E29 -> 22168900 | G29: =(F29-C29)/100000 -> -178.211 | H29: =SUMIF('Payment Schedule'!$F$5:$F$41,VALUE(A29),'Payment Schedule'!$I$5:$I$41) -> 25494235
A30: 2029 | C30: =SUMIF('Original Offer'!$B$5:$B$19,VALUE(A30),'Original Offer'!$F$5:$F$19) -> 49530000 | D30: =SUMIFS('Payment Schedule'!$G$5:$G$41,'Payment Schedule'!$F$5:$F$41,VALUE(A30),'Payment Schedule'!$A$5:$A$41,"Rollout") -> 44274000 | E30: =SUMIFS('Payment Schedule'!$G$5:$G$41,'Payment Schedule'!$F$5:$F$41,VALUE(A30),'Payment Schedule'!$A$5:$A$41,"Maintenance") -> 0 | F30: =D30+E30 -> 44274000 | G30: =(F30-C30)/100000 -> -52.56 | H30: =SUMIF('Payment Schedule'!$F$5:$F$41,VALUE(A30),'Payment Schedule'!$I$5:$I$41) -> 50915100
A31: 2030 | C31: =SUMIF('Original Offer'!$B$5:$B$19,VALUE(A31),'Original Offer'!$F$5:$F$19) -> 37620000 | D31: =SUMIFS('Payment Schedule'!$G$5:$G$41,'Payment Schedule'!$F$5:$F$41,VALUE(A31),'Payment Schedule'!$A$5:$A$41,"Rollout") -> 1353400 | E31: =SUMIFS('Payment Schedule'!$G$5:$G$41,'Payment Schedule'!$F$5:$F$41,VALUE(A31),'Payment Schedule'!$A$5:$A$41,"Maintenance") -> 37620000 | F31: =D31+E31 -> 38973400 | G31: =(F31-C31)/100000 -> 13.534 | H31: =SUMIF('Payment Schedule'!$F$5:$F$41,VALUE(A31),'Payment Schedule'!$I$5:$I$41) -> 44819410
A32: 2031 | C32: =SUMIF('Original Offer'!$B$5:$B$19,VALUE(A32),'Original Offer'!$F$5:$F$19) -> 37620000 | D32: =SUMIFS('Payment Schedule'!$G$5:$G$41,'Payment Schedule'!$F$5:$F$41,VALUE(A32),'Payment Schedule'!$A$5:$A$41,"Rollout") -> 0 | E32: =SUMIFS('Payment Schedule'!$G$5:$G$41,'Payment Schedule'!$F$5:$F$41,VALUE(A32),'Payment Schedule'!$A$5:$A$41,"Maintenance") -> 37620000 | F32: =D32+E32 -> 37620000 | G32: =(F32-C32)/100000 -> 0 | H32: =SUMIF('Payment Schedule'!$F$5:$F$41,VALUE(A32),'Payment Schedule'!$I$5:$I$41) -> 43263000
A33: Total | C33: =SUM(C27:C32) -> 186905000 | D33: =SUM(D27:D32) -> 111665000 | E33: =SUM(E27:E32) -> 75240000 | F33: =SUM(F27:F32) -> 186905000 | G33: =ROUND(SUM(G27:G32),2) -> 0 | H33: =SUM(H27:H32) -> 214940750
B34: Check: revised total equals proposal total | C34: =IF(ABS(F33-C33)<1,"OK","ERROR") -> OK
A36: Checks
B37: Milestone percentages total 100% | C37: =Inputs!B27 -> OK
B38: Work Volume allocation equals development pool | C38: ='Work Volume'!P54 -> OK
B39: Package total equals rollout total | C39: =Packages!F14 -> OK
B40: Every Work Volume row assigned to a package | C40: =Packages!F15 -> OK
B41: All rollout packages within the 2-crore cap | C41: =IF(COUNTIF(Packages!J5:J12,"EXCEEDS")=0,"OK","EXCEEDS") -> OK
B42: Payment schedule reconciles to rollout and maintenance | C42: ='Payment Schedule'!G45 -> OK
B43: Each maintenance tranche within the cap | C43: ='Payment Schedule'!G46 -> OK
B44: Original offer recomputes to proposal totals | C44: ='Original Offer'!F23 -> OK
B45: Accounts, CM, PCR and labs (WP1–WP3) live by the Dec 2027 deadline | C45: =IF(MAX(Packages!U6:U8)<=Inputs!B15,"OK","LATE") -> OK

Sheet Inputs
A1: Inputs and assumptions
A2: Blue = input you can change. Yellow = BSTI assumption to confirm. Black = formula.
A4: Rollout total, OrangeBD Financial Proposal V4 (BDT, excl. VAT) | B4: 111665000 | C4: Source: Financial Proposal V4, p.4 (Aug 2026 – Dec 2029). Kept unchanged as instructed.
A5: Interim O&M of 5 live services, Aug–Dec 2026 (BDT) | B5: 1625000 | C5: Source: Financial Proposal V4, p.4 (5 services × 65,000 × 5 months = 16,25,000). Kept as a separate O&M package, not development. Set to 0 to allocate the whole rollout by work volume.
A6: Development pool allocated by work volume (BDT) | B6: =B4-B5 -> 110040000 | C6: Formula
A7: Maximum value per approval (BDT) | B7: 20000000 | C7: User instruction: at most 2 crore can be approved at a time.
A8: VAT and taxes for the approval check | B8: 0.15 | C8: Assumption: 15% standard VAT. Proposal prices exclude VAT (p.3). Confirm the applicable VAT/AIT rate with Accounts; set to 0 if the 2-crore limit applies to the price excluding VAT.
A9: Apply the cap to the value including VAT? (Y/N) | B9: Y | C9: Y = check package value incl. VAT against the cap (safer). N = check value excl. VAT.
A10: Maintenance total 2030–2031 (BDT, excl. VAT) | B10: 75240000 | C10: Source: Financial Proposal V4, p.5 (33 × 95,000 × 24 = 7,52,40,000). Unchanged.
A11: Maintenance period (months) | B11: 24 | C11: Jan 2030 – Dec 2031
A12: Maintenance months per approval | B12: 3 | C12: Quarterly, matching the proposal's payment mode (p.3). 6 months fits the cap only if VAT is excluded from it.
A13: Maintenance start | B13: 47484 | C13: Source: Financial Proposal V4, p.5
A14: Round package values to (digits, -3 = nearest 1,000) | B14: -3 | C14: Last package absorbs the rounding so the total stays exactly equal to the rollout total.
A15: Deadline: Accounts, CM, PCR and lab testing fully running | B15: 46752 | C15: User instruction (19 Oct 2026): lab testing cannot be delayed; CM + PCR + labs + Accounts must be fully running within December 2027. Applies to WP1–WP3.
A16: Work-type weighting factor | B16: Factor | C16: Meaning
A17: N | B17: 1 | C17: N = New build: first workflow of its family; full feature count counts as work.
A18: V | B18: 0.5 | C18: V = Variant: renewal / brand inclusion / re-certification / scope inclusion of a family built in the same package. Session 1 found these SRS sections 85–99% identical text (difflib), so most of the work is configuration.
A19: L | B19: 0.5 | C19: L = Live in v1: already running (HRM, Payroll, Standards sale, CM new, PCR new). Work is re-platforming into v2: 23-office organogram, SSO, shared engines and data migration.
C20: Set every factor to 1.00 to allocate purely by the deck's feature counts.
A22: Payment milestone (each development package) | B22: % of package | C22: Acceptance evidence
A23: M1 Design & prototype sign-off | B23: 0.2 | C23: Package SRS detail (forms, fields, fee rules, desk roles, acceptance criteria) and clickable prototype approved by the wing.
A24: M2 UAT acceptance | B24: 0.3 | C24: UAT signed by the wing focal point and ICT; zero open critical defects.
A25: M3 Go-live | B25: 0.4 | C25: All services in the package live at HQ and the relevant regional offices with real transactions; data migrated; training done.
A26: M4 End of stabilisation | B26: 0.1 | C26: Retention: released after the stabilisation period with SLA met; source code and documentation deposited.
A27: Check: milestones total 100% | B27: =IF(ROUND(SUM(B23:B26),4)=1,"OK","ERROR") -> OK

Sheet Work Volume
A1: Work volume and cost allocation by priority (serial.docx order)
A2: Volume = feature count per service from OrangeBD's BSTI 2.0.pptx (slides 14–46). Work units = features used × work-type factor. Each row's cost = its share of work units × development pool. Yellow = BSTI estimate where the SRS/deck gives no scope.
A4: Priority | B4: Serial ref | C4: Service / module (as in serial.docx) | D4: Package | E4: Deck service | F4: Deck service title | G4: Modules (deck) | H4: Features (deck, parent service) | I4: Features used | J4: Basis for features used | K4: Work type (N/V/L) | L4: Factor | M4: Include? (Y/N) | N4: Work units | O4: Share of work | P4: Allocated (BDT) | Q4: Allocated (lakh)
A5: 1 | B5: 1 | C5: BSTI 2.0 Transformation: common platform (unified portal & SSO, 23-office organogram, workflow / fee-payment / certificate-QR engines, v1 data migration) | D5: WP1 | E5: — | F5: Not a separate deck service (shown in SRS architecture, p.17) | I5: 60 | J5: BSTI estimate: no feature list in SRS | K5: N | L5: =INDEX(Inputs!$B$17:$B$19,MATCH(K5,Inputs!$A$17:$A$19,0)) -> 1 | M5: Y | N5: =IF(M5="Y",I5*L5,0) -> 60 | O5: =IF($N$53=0,0,N5/$N$53) -> 0.033167496 | P5: =O5*Inputs!$B$6 -> 3649751.2 | Q5: =P5/100000 -> 36.497512
A6: 1 | B6: 1(i) | C6: HRM & Leave | D6: WP1 | E6: S01 | F6: HRM & Leave Management | G6: 11 | H6: 49 | I6: =H6 -> 49 | J6: Deck slide 14 | K6: L | L6: =INDEX(Inputs!$B$17:$B$19,MATCH(K6,Inputs!$A$17:$A$19,0)) -> 0.5 | M6: Y | N6: =IF(M6="Y",I6*L6,0) -> 24.5 | O6: =IF($N$53=0,0,N6/$N$53) -> 0.013543394 | P6: =O6*Inputs!$B$6 -> 1490315.1 | Q6: =P6/100000 -> 14.903151
A7: 1 | B7: 1(ii) | C7: Payroll | D7: WP1 | E7: S02 | F7: Payroll Management | G7: 15 | H7: 84 | I7: =H7 -> 84 | J7: Deck slide 15 | K7: L | L7: =INDEX(Inputs!$B$17:$B$19,MATCH(K7,Inputs!$A$17:$A$19,0)) -> 0.5 | M7: Y | N7: =IF(M7="Y",I7*L7,0) -> 42 | O7: =IF($N$53=0,0,N7/$N$53) -> 0.023217247 | P7: =O7*Inputs!$B$6 -> 2554825.9 | Q7: =P7/100000 -> 25.548259
A8: 1 | B8: 1(iii) | C8: BDS sell (Standards sale) | D8: WP1 | E8: S23* | F8: Replaces S23 slot; no scope in SRS or deck | I8: 40 | J8: BSTI estimate: move into portal/SSO, link to CM application, shared payment | K8: L | L8: =INDEX(Inputs!$B$17:$B$19,MATCH(K8,Inputs!$A$17:$A$19,0)) -> 0.5 | M8: Y | N8: =IF(M8="Y",I8*L8,0) -> 20 | O8: =IF($N$53=0,0,N8/$N$53) -> 0.011055832 | P8: =O8*Inputs!$B$6 -> 1216583.7 | Q8: =P8/100000 -> 12.165837
A9: 2 | B9: 2 | C9: Accounts | D9: WP1 | E9: S03 | F9: Finance & Accounts Management | G9: 10 | H9: 57 | I9: =H9 -> 57 | J9: Deck slide 16 | K9: N | L9: =INDEX(Inputs!$B$17:$B$19,MATCH(K9,Inputs!$A$17:$A$19,0)) -> 1 | M9: Y | N9: =IF(M9="Y",I9*L9,0) -> 57 | O9: =IF($N$53=0,0,N9/$N$53) -> 0.031509121 | P9: =O9*Inputs!$B$6 -> 3467263.7 | Q9: =P9/100000 -> 34.672637
A10: 3 | B10: 3(i) | C10: CM Non-Scope Products (new licence) | D10: WP2 | E10: S05 | F10: CM Mandatory New Certification | G10: 12 | H10: 46 | I10: =H10 -> 46 | J10: Deck slide 18 | K10: L | L10: =INDEX(Inputs!$B$17:$B$19,MATCH(K10,Inputs!$A$17:$A$19,0)) -> 0.5 | M10: Y | N10: =IF(M10="Y",I10*L10,0) -> 23 | O10: =IF($N$53=0,0,N10/$N$53) -> 0.012714207 | P10: =O10*Inputs!$B$6 -> 1399071.3 | Q10: =P10/100000 -> 13.990713
A11: 3 | B11: 3(ii) | C11: CM Non-Scope Product Renewal | D11: WP2 | E11: S06 | F11: CM Mandatory Renewal | G11: 12 | H11: 46 | I11: =H11 -> 46 | J11: Deck slide 19 | K11: V | L11: =INDEX(Inputs!$B$17:$B$19,MATCH(K11,Inputs!$A$17:$A$19,0)) -> 0.5 | M11: Y | N11: =IF(M11="Y",I11*L11,0) -> 23 | O11: =IF($N$53=0,0,N11/$N$53) -> 0.012714207 | P11: =O11*Inputs!$B$6 -> 1399071.3 | Q11: =P11/100000 -> 13.990713
A12: 3 | B12: 3(iii) | C12: CM Non-Scope Brand Inclusion | D12: WP2 | E12: S07 | F12: CM Mandatory Brand Inclusion | G12: 12 | H12: 46 | I12: =H12 -> 46 | J12: Deck slide 20 | K12: V | L12: =INDEX(Inputs!$B$17:$B$19,MATCH(K12,Inputs!$A$17:$A$19,0)) -> 0.5 | M12: Y | N12: =IF(M12="Y",I12*L12,0) -> 23 | O12: =IF($N$53=0,0,N12/$N$53) -> 0.012714207 | P12: =O12*Inputs!$B$6 -> 1399071.3 | Q12: =P12/100000 -> 13.990713
A13: 3 | B13: 3(iv) | C13: CM Scope Product | D13: WP2 | E13: S08 | F13: CM Scope New Certification | G13: 16 | H13: 83 | I13: =H13 -> 83 | J13: Deck slide 21 | K13: N | L13: =INDEX(Inputs!$B$17:$B$19,MATCH(K13,Inputs!$A$17:$A$19,0)) -> 1 | M13: Y | N13: =IF(M13="Y",I13*L13,0) -> 83 | O13: =IF($N$53=0,0,N13/$N$53) -> 0.045881703 | P13: =O13*Inputs!$B$6 -> 5048822.6 | Q13: =P13/100000 -> 50.488226
A14: 3 | B14: 3(v) | C14: CM Scope Product Renewal | D14: WP2 | E14: S09 | F14: CM Scope Renewal Certification | G14: 16 | H14: 83 | I14: =H14 -> 83 | J14: Deck slide 22 | K14: V | L14: =INDEX(Inputs!$B$17:$B$19,MATCH(K14,Inputs!$A$17:$A$19,0)) -> 0.5 | M14: Y | N14: =IF(M14="Y",I14*L14,0) -> 41.5 | O14: =IF($N$53=0,0,N14/$N$53) -> 0.022940851 | P14: =O14*Inputs!$B$6 -> 2524411.3 | Q14: =P14/100000 -> 25.244113
A15: 3 | B15: 3(vi) | C15: CM Scope Brand Inclusion | D15: WP2 | E15: S10 | F15: CM Scope Brand Inclusion | G15: 16 | H15: 83 | I15: =H15 -> 83 | J15: Deck slide 23 | K15: V | L15: =INDEX(Inputs!$B$17:$B$19,MATCH(K15,Inputs!$A$17:$A$19,0)) -> 0.5 | M15: Y | N15: =IF(M15="Y",I15*L15,0) -> 41.5 | O15: =IF($N$53=0,0,N15/$N$53) -> 0.022940851 | P15: =O15*Inputs!$B$6 -> 2524411.3 | Q15: =P15/100000 -> 25.244113
A16: 3 | B16: Footnote | C16: All types of Suspension / Cancellation / Withdrawal of certificates and licences (common module, reused by every later package) | D16: WP2 | E16: — | F16: Not in deck; MSC/CM gaps flagged by wings in 2025 | I16: 30 | J16: BSTI estimate | K16: N | L16: =INDEX(Inputs!$B$17:$B$19,MATCH(K16,Inputs!$A$17:$A$19,0)) -> 1 | M16: Y | N16: =IF(M16="Y",I16*L16,0) -> 30 | O16: =IF($N$53=0,0,N16/$N$53) -> 0.016583748 | P16: =O16*Inputs!$B$6 -> 1824875.6 | Q16: =P16/100000 -> 18.248756
A17: 4 | B17: 4 | C17: Chemical Testing | D17: WP3 | E17: S14 | F17: Chemical Testing | G17: 20 | H17: 67 | I17: =H17 -> 67 | J17: Deck slide 27 | K17: N | L17: =INDEX(Inputs!$B$17:$B$19,MATCH(K17,Inputs!$A$17:$A$19,0)) -> 1 | M17: Y | N17: =IF(M17="Y",I17*L17,0) -> 67 | O17: =IF($N$53=0,0,N17/$N$53) -> 0.037037037 | P17: =O17*Inputs!$B$6 -> 4075555.6 | Q17: =P17/100000 -> 40.755556
A18: 5 | B18: 5 | C18: Physical Testing | D18: WP3 | E18: S15 | F18: Physical Testing | G18: 10 | H18: 72 | I18: =H18 -> 72 | J18: Deck slide 28 | K18: N | L18: =INDEX(Inputs!$B$17:$B$19,MATCH(K18,Inputs!$A$17:$A$19,0)) -> 1 | M18: Y | N18: =IF(M18="Y",I18*L18,0) -> 72 | O18: =IF($N$53=0,0,N18/$N$53) -> 0.039800995 | P18: =O18*Inputs!$B$6 -> 4379701.5 | Q18: =P18/100000 -> 43.797015
A19: 6 | B19: 6 | C19: Energy Meter Testing | D19: WP3 | E19: S16 | F19: Physical Lab – Energy Meter | G19: 12 | H19: 71 | I19: =H19 -> 71 | J19: Deck slide 29 | K19: N | L19: =INDEX(Inputs!$B$17:$B$19,MATCH(K19,Inputs!$A$17:$A$19,0)) -> 1 | M19: Y | N19: =IF(M19="Y",I19*L19,0) -> 71 | O19: =IF($N$53=0,0,N19/$N$53) -> 0.039248203 | P19: =O19*Inputs!$B$6 -> 4318872.3 | Q19: =P19/100000 -> 43.188723
A20: 7 | B20: 7(i) | C20: PCR new | D20: WP3 | E20: S19 | F20: PCR Registration New | G20: 13 | H20: 48 | I20: =H20 -> 48 | J20: Deck slide 32 | K20: L | L20: =INDEX(Inputs!$B$17:$B$19,MATCH(K20,Inputs!$A$17:$A$19,0)) -> 0.5 | M20: Y | N20: =IF(M20="Y",I20*L20,0) -> 24 | O20: =IF($N$53=0,0,N20/$N$53) -> 0.013266998 | P20: =O20*Inputs!$B$6 -> 1459900.5 | Q20: =P20/100000 -> 14.599005
A21: 7 | B21: 7(ii) | C21: PCR Renewal | D21: WP3 | E21: S20 | F21: PCR Registration Renewal | G21: 13 | H21: 48 | I21: =H21 -> 48 | J21: Deck slide 33 | K21: V | L21: =INDEX(Inputs!$B$17:$B$19,MATCH(K21,Inputs!$A$17:$A$19,0)) -> 0.5 | M21: Y | N21: =IF(M21="Y",I21*L21,0) -> 24 | O21: =IF($N$53=0,0,N21/$N$53) -> 0.013266998 | P21: =O21*Inputs!$B$6 -> 1459900.5 | Q21: =P21/100000 -> 14.599005
A22: 7 | B22: 7(iii) | C22: PCR Brand Inclusion | D22: WP3 | E22: S21 | F22: PCR Brand Inclusion | G22: 13 | H22: 45 | I22: =H22 -> 45 | J22: Deck slide 34 | K22: V | L22: =INDEX(Inputs!$B$17:$B$19,MATCH(K22,Inputs!$A$17:$A$19,0)) -> 0.5 | M22: Y | N22: =IF(M22="Y",I22*L22,0) -> 22.5 | O22: =IF($N$53=0,0,N22/$N$53) -> 0.012437811 | P22: =O22*Inputs!$B$6 -> 1368656.7 | Q22: =P22/100000 -> 13.686567
A23: 8 | B23: 8 | C23: Mobile Court | D23: WP4 | E23: S33 | F23: Mobile Court & Surveillance e-Service | G23: 8 | H23: 49 | I23: 26 | J23: Deck slide 46 modules: Mobile Court 18 + Product 5 + Tracking 3 | K23: N | L23: =INDEX(Inputs!$B$17:$B$19,MATCH(K23,Inputs!$A$17:$A$19,0)) -> 1 | M23: Y | N23: =IF(M23="Y",I23*L23,0) -> 26 | O23: =IF($N$53=0,0,N23/$N$53) -> 0.014372582 | P23: =O23*Inputs!$B$6 -> 1581558.9 | Q23: =P23/100000 -> 15.815589
A24: 9 | B24: 9(i) | C24: Surveillance – Operational Activities | D24: WP4 | E24: S33 | F24: Mobile Court & Surveillance e-Service | G24: 8 | H24: 49 | I24: 11.5 | J24: Deck slide 46: remaining 23 features (Surveillance 10, Sample 7, Test report 2, Admin 2, Workflow 2) split equally | K24: N | L24: =INDEX(Inputs!$B$17:$B$19,MATCH(K24,Inputs!$A$17:$A$19,0)) -> 1 | M24: Y | N24: =IF(M24="Y",I24*L24,0) -> 11.5 | O24: =IF($N$53=0,0,N24/$N$53) -> 0.0063571034 | P24: =O24*Inputs!$B$6 -> 699535.66 | Q24: =P24/100000 -> 6.9953566
A25: 9 | B25: 9(ii) | C25: Surveillance – List of Illegal Establishments | D25: WP4 | E25: S33 | F25: Mobile Court & Surveillance e-Service | G25: 8 | H25: 49 | I25: 11.5 | J25: As above | K25: N | L25: =INDEX(Inputs!$B$17:$B$19,MATCH(K25,Inputs!$A$17:$A$19,0)) -> 1 | M25: Y | N25: =IF(M25="Y",I25*L25,0) -> 11.5 | O25: =IF($N$53=0,0,N25/$N$53) -> 0.0063571034 | P25: =O25*Inputs!$B$6 -> 699535.66 | Q25: =P25/100000 -> 6.9953566
A26: 10 | B26: 10(i) | C26: Verification – Petrol Pump | D26: WP4 | E26: S32 | F26: Verification Service | G26: 12 | H26: 48 | I26: =H26/4 -> 12 | J26: Deck slide 45; split equally over 4 sub-types | K26: N | L26: =INDEX(Inputs!$B$17:$B$19,MATCH(K26,Inputs!$A$17:$A$19,0)) -> 1 | M26: Y | N26: =IF(M26="Y",I26*L26,0) -> 12 | O26: =IF($N$53=0,0,N26/$N$53) -> 0.0066334992 | P26: =O26*Inputs!$B$6 -> 729950.25 | Q26: =P26/100000 -> 7.2995025
A27: 10 | B27: 10(ii) | C27: Verification – Weighing Scale (general) | D27: WP4 | E27: S32 | F27: Verification Service | G27: 12 | H27: 48 | I27: =H27/4 -> 12 | J27: As above | K27: N | L27: =INDEX(Inputs!$B$17:$B$19,MATCH(K27,Inputs!$A$17:$A$19,0)) -> 1 | M27: Y | N27: =IF(M27="Y",I27*L27,0) -> 12 | O27: =IF($N$53=0,0,N27/$N$53) -> 0.0066334992 | P27: =O27*Inputs!$B$6 -> 729950.25 | Q27: =P27/100000 -> 7.2995025
A28: 10 | B28: 10(iii) | C28: Verification – Weighing Scale (Association) | D28: WP4 | E28: S32 | F28: Verification Service | G28: 12 | H28: 48 | I28: =H28/4 -> 12 | J28: As above | K28: N | L28: =INDEX(Inputs!$B$17:$B$19,MATCH(K28,Inputs!$A$17:$A$19,0)) -> 1 | M28: Y | N28: =IF(M28="Y",I28*L28,0) -> 12 | O28: =IF($N$53=0,0,N28/$N$53) -> 0.0066334992 | P28: =O28*Inputs!$B$6 -> 729950.25 | Q28: =P28/100000 -> 7.2995025
A29: 10 | B29: 10(iv) | C29: Verification – Weighbridge | D29: WP4 | E29: S32 | F29: Verification Service | G29: 12 | H29: 48 | I29: =H29/4 -> 12 | J29: As above | K29: N | L29: =INDEX(Inputs!$B$17:$B$19,MATCH(K29,Inputs!$A$17:$A$19,0)) -> 1 | M29: Y | N29: =IF(M29="Y",I29*L29,0) -> 12 | O29: =IF($N$53=0,0,N29/$N$53) -> 0.0066334992 | P29: =O29*Inputs!$B$6 -> 729950.25 | Q29: =P29/100000 -> 7.2995025
A30: 11 | B30: 11(i) | C30: Tank Calibration – Tank Lorry | D30: WP4 | E30: S26 | F30: Tank Lorry Calibration | G30: 12 | H30: 49 | I30: =H30/2 -> 24.5 | J30: Deck slide 39; split equally over 2 sub-types | K30: N | L30: =INDEX(Inputs!$B$17:$B$19,MATCH(K30,Inputs!$A$17:$A$19,0)) -> 1 | M30: Y | N30: =IF(M30="Y",I30*L30,0) -> 24.5 | O30: =IF($N$53=0,0,N30/$N$53) -> 0.013543394 | P30: =O30*Inputs!$B$6 -> 1490315.1 | Q30: =P30/100000 -> 14.903151
A31: 11 | B31: 11(ii) | C31: Tank Calibration – Road-Tanker | D31: WP4 | E31: S26 | F31: Tank Lorry Calibration | G31: 12 | H31: 49 | I31: =H31/2 -> 24.5 | J31: As above | K31: N | L31: =INDEX(Inputs!$B$17:$B$19,MATCH(K31,Inputs!$A$17:$A$19,0)) -> 1 | M31: Y | N31: =IF(M31="Y",I31*L31,0) -> 24.5 | O31: =IF($N$53=0,0,N31/$N$53) -> 0.013543394 | P31: =O31*Inputs!$B$6 -> 1490315.1 | Q31: =P31/100000 -> 14.903151
A32: 12 | B32: 12(i) | C32: Metrology License New | D32: WP4 | E32: S24 | F32: Metrology License Issue | G32: 13 | H32: 54 | I32: =H32 -> 54 | J32: Deck slide 37 | K32: N | L32: =INDEX(Inputs!$B$17:$B$19,MATCH(K32,Inputs!$A$17:$A$19,0)) -> 1 | M32: Y | N32: =IF(M32="Y",I32*L32,0) -> 54 | O32: =IF($N$53=0,0,N32/$N$53) -> 0.029850746 | P32: =O32*Inputs!$B$6 -> 3284776.1 | Q32: =P32/100000 -> 32.847761
A33: 12 | B33: 12(ii) | C33: Metrology License Renewal | D33: WP4 | E33: S25 | F33: Metrology License Renewal | G33: 13 | H33: 54 | I33: =H33 -> 54 | J33: Deck slide 38 | K33: V | L33: =INDEX(Inputs!$B$17:$B$19,MATCH(K33,Inputs!$A$17:$A$19,0)) -> 0.5 | M33: Y | N33: =IF(M33="Y",I33*L33,0) -> 27 | O33: =IF($N$53=0,0,N33/$N$53) -> 0.014925373 | P33: =O33*Inputs!$B$6 -> 1642388.1 | Q33: =P33/100000 -> 16.423881
A34: 13 | B34: 13(i) | C34: Storage Tank Calibration – Underground | D34: WP4 | E34: S30 | F34: Storage Tank Calibration | G34: 13 | H34: 58 | I34: =H34/5 -> 11.6 | J34: Deck slide 43; split equally over 5 sub-types | K34: N | L34: =INDEX(Inputs!$B$17:$B$19,MATCH(K34,Inputs!$A$17:$A$19,0)) -> 1 | M34: Y | N34: =IF(M34="Y",I34*L34,0) -> 11.6 | O34: =IF($N$53=0,0,N34/$N$53) -> 0.0064123825 | P34: =O34*Inputs!$B$6 -> 705618.57 | Q34: =P34/100000 -> 7.0561857
A35: 13 | B35: 13(ii) | C35: Storage Tank Calibration – Overhead | D35: WP4 | E35: S30 | F35: Storage Tank Calibration | G35: 13 | H35: 58 | I35: =H35/5 -> 11.6 | J35: As above | K35: N | L35: =INDEX(Inputs!$B$17:$B$19,MATCH(K35,Inputs!$A$17:$A$19,0)) -> 1 | M35: Y | N35: =IF(M35="Y",I35*L35,0) -> 11.6 | O35: =IF($N$53=0,0,N35/$N$53) -> 0.0064123825 | P35: =O35*Inputs!$B$6 -> 705618.57 | Q35: =P35/100000 -> 7.0561857
A36: 13 | B36: 13(iii) | C36: Storage Tank Calibration – Oil-Tanker | D36: WP4 | E36: S30 | F36: Storage Tank Calibration | G36: 13 | H36: 58 | I36: =H36/5 -> 11.6 | J36: As above | K36: N | L36: =INDEX(Inputs!$B$17:$B$19,MATCH(K36,Inputs!$A$17:$A$19,0)) -> 1 | M36: Y | N36: =IF(M36="Y",I36*L36,0) -> 11.6 | O36: =IF($N$53=0,0,N36/$N$53) -> 0.0064123825 | P36: =O36*Inputs!$B$6 -> 705618.57 | Q36: =P36/100000 -> 7.0561857
A37: 13 | B37: 13(iv) | C37: Storage Tank Calibration – Barge | D37: WP4 | E37: S30 | F37: Storage Tank Calibration | G37: 13 | H37: 58 | I37: =H37/5 -> 11.6 | J37: As above | K37: N | L37: =INDEX(Inputs!$B$17:$B$19,MATCH(K37,Inputs!$A$17:$A$19,0)) -> 1 | M37: Y | N37: =IF(M37="Y",I37*L37,0) -> 11.6 | O37: =IF($N$53=0,0,N37/$N$53) -> 0.0064123825 | P37: =O37*Inputs!$B$6 -> 705618.57 | Q37: =P37/100000 -> 7.0561857
A38: 13 | B38: 13(v) | C38: Storage Tank Calibration – Lighter | D38: WP4 | E38: S30 | F38: Storage Tank Calibration | G38: 13 | H38: 58 | I38: =H38/5 -> 11.6 | J38: As above | K38: N | L38: =INDEX(Inputs!$B$17:$B$19,MATCH(K38,Inputs!$A$17:$A$19,0)) -> 1 | M38: Y | N38: =IF(M38="Y",I38*L38,0) -> 11.6 | O38: =IF($N$53=0,0,N38/$N$53) -> 0.0064123825 | P38: =O38*Inputs!$B$6 -> 705618.57 | Q38: =P38/100000 -> 7.0561857
A39: 14 | B39: 14(i) | C39: MSC Issue | D39: WP5 | E39: S17 | F39: MSC Certification | G39: 24 | H39: 174 | I39: =H39 -> 174 | J39: Deck slide 30 | K39: N | L39: =INDEX(Inputs!$B$17:$B$19,MATCH(K39,Inputs!$A$17:$A$19,0)) -> 1 | M39: Y | N39: =IF(M39="Y",I39*L39,0) -> 174 | O39: =IF($N$53=0,0,N39/$N$53) -> 0.096185738 | P39: =O39*Inputs!$B$6 -> 10584279 | Q39: =P39/100000 -> 105.84279
A40: 14 | B40: 14(ii) | C40: MSC Renewal | D40: WP5 | E40: S18 | F40: MSC Re-certification | G40: 14 | H40: 136 | I40: =H40 -> 136 | J40: Deck slide 31 | K40: V | L40: =INDEX(Inputs!$B$17:$B$19,MATCH(K40,Inputs!$A$17:$A$19,0)) -> 0.5 | M40: Y | N40: =IF(M40="Y",I40*L40,0) -> 68 | O40: =IF($N$53=0,0,N40/$N$53) -> 0.037589829 | P40: =O40*Inputs!$B$6 -> 4136384.7 | Q40: =P40/100000 -> 41.363847
A41: 14 | B41: 14(iii) | C41: MSC Scope Inclusion | D41: WP5 | E41: — | F41: Not in deck or SRS | I41: 50 | J41: BSTI estimate (similar to a brand / scope inclusion) | K41: V | L41: =INDEX(Inputs!$B$17:$B$19,MATCH(K41,Inputs!$A$17:$A$19,0)) -> 0.5 | M41: Y | N41: =IF(M41="Y",I41*L41,0) -> 25 | O41: =IF($N$53=0,0,N41/$N$53) -> 0.01381979 | P41: =O41*Inputs!$B$6 -> 1520729.7 | Q41: =P41/100000 -> 15.207297
A42: 15 | B42: 15(i) | C42: Halal Certificate New | D42: WP6 | E42: S11 | F42: CM Halal Certification | G42: 16 | H42: 86 | I42: =H42 -> 86 | J42: Deck slide 24 | K42: N | L42: =INDEX(Inputs!$B$17:$B$19,MATCH(K42,Inputs!$A$17:$A$19,0)) -> 1 | M42: Y | N42: =IF(M42="Y",I42*L42,0) -> 86 | O42: =IF($N$53=0,0,N42/$N$53) -> 0.047540077 | P42: =O42*Inputs!$B$6 -> 5231310.1 | Q42: =P42/100000 -> 52.313101
A43: 15 | B43: 15(ii) | C43: Halal Recertification | D43: WP6 | E43: S12 | F43: CM Halal Renewal Certification | G43: 16 | H43: 86 | I43: =H43 -> 86 | J43: Deck slide 25 | K43: V | L43: =INDEX(Inputs!$B$17:$B$19,MATCH(K43,Inputs!$A$17:$A$19,0)) -> 0.5 | M43: Y | N43: =IF(M43="Y",I43*L43,0) -> 43 | O43: =IF($N$53=0,0,N43/$N$53) -> 0.023770039 | P43: =O43*Inputs!$B$6 -> 2615655.1 | Q43: =P43/100000 -> 26.156551
A44: 15 | B44: 15(iii) | C44: Halal Brand Inclusion | D44: WP6 | E44: S13 | F44: CM Halal Brand Inclusion | G44: 16 | H44: 86 | I44: =H44 -> 86 | J44: Deck slide 26 | K44: V | L44: =INDEX(Inputs!$B$17:$B$19,MATCH(K44,Inputs!$A$17:$A$19,0)) -> 0.5 | M44: Y | N44: =IF(M44="Y",I44*L44,0) -> 43 | O44: =IF($N$53=0,0,N44/$N$53) -> 0.023770039 | P44: =O44*Inputs!$B$6 -> 2615655.1 | Q44: =P44/100000 -> 26.156551
A45: 16 | B45: 16(i) | C45: LPG Bottling Plant / LPG Filling / Fuel Filling Station – New Registration | D45: WP6 | E45: S27 | F45: LPG / Fuel Station Registration | G45: 12 | H45: 53 | I45: =H45 -> 53 | J45: Deck slide 40 | K45: N | L45: =INDEX(Inputs!$B$17:$B$19,MATCH(K45,Inputs!$A$17:$A$19,0)) -> 1 | M45: Y | N45: =IF(M45="Y",I45*L45,0) -> 53 | O45: =IF($N$53=0,0,N45/$N$53) -> 0.029297955 | P45: =O45*Inputs!$B$6 -> 3223946.9 | Q45: =P45/100000 -> 32.239469
A46: 16 | B46: 16(ii) | C46: LPG Bottling Plant / LPG Filling / Fuel Filling Station – Renewal | D46: WP6 | E46: S28 | F46: LPG / Fuel Station Renewal | G46: 12 | H46: 53 | I46: =H46 -> 53 | J46: Deck slide 41 | K46: V | L46: =INDEX(Inputs!$B$17:$B$19,MATCH(K46,Inputs!$A$17:$A$19,0)) -> 0.5 | M46: Y | N46: =IF(M46="Y",I46*L46,0) -> 26.5 | O46: =IF($N$53=0,0,N46/$N$53) -> 0.014648977 | P46: =O46*Inputs!$B$6 -> 1611973.5 | Q46: =P46/100000 -> 16.119735
A47: 17 | B47: 17 | C47: Case Management | D47: WP6 | E47: S04 | F47: Case Management System | G47: 8 | H47: 34 | I47: =H47 -> 34 | J47: Deck slide 17 | K47: N | L47: =INDEX(Inputs!$B$17:$B$19,MATCH(K47,Inputs!$A$17:$A$19,0)) -> 1 | M47: Y | N47: =IF(M47="Y",I47*L47,0) -> 34 | O47: =IF($N$53=0,0,N47/$N$53) -> 0.018794914 | P47: =O47*Inputs!$B$6 -> 2068192.4 | Q47: =P47/100000 -> 20.681924
A48: 18 | B48: 18 | C48: I&S Metrology Calibration (NML) | D48: WP7 | E48: S31 | F48: Industrial & Scientific Metrology Calibration | G48: 14 | H48: 59 | I48: =H48 -> 59 | J48: Deck slide 44 | K48: N | L48: =INDEX(Inputs!$B$17:$B$19,MATCH(K48,Inputs!$A$17:$A$19,0)) -> 1 | M48: Y | N48: =IF(M48="Y",I48*L48,0) -> 59 | O48: =IF($N$53=0,0,N48/$N$53) -> 0.032614704 | P48: =O48*Inputs!$B$6 -> 3588922.1 | Q48: =P48/100000 -> 35.889221
A49: 19 | B49: 19 | C49: Building (flat) / Establishment Measurement | D49: WP7 | E49: S29 | F49: Building / Establishment Measurement | G49: 12 | H49: 53 | I49: =H49 -> 53 | J49: Deck slide 42 | K49: N | L49: =INDEX(Inputs!$B$17:$B$19,MATCH(K49,Inputs!$A$17:$A$19,0)) -> 1 | M49: Y | N49: =IF(M49="Y",I49*L49,0) -> 53 | O49: =IF($N$53=0,0,N49/$N$53) -> 0.029297955 | P49: =O49*Inputs!$B$6 -> 3223946.9 | Q49: =P49/100000 -> 32.239469
A50: 20 | B50: 20 | C50: API integration with BSW (Bangladesh Single Window) | D50: WP7 | E50: — | F50: Not in deck or SRS | I50: 30 | J50: BSTI estimate | K50: N | L50: =INDEX(Inputs!$B$17:$B$19,MATCH(K50,Inputs!$A$17:$A$19,0)) -> 1 | M50: Y | N50: =IF(M50="Y",I50*L50,0) -> 30 | O50: =IF($N$53=0,0,N50/$N$53) -> 0.016583748 | P50: =O50*Inputs!$B$6 -> 1824875.6 | Q50: =P50/100000 -> 18.248756
A51: 21 | B51: Footnote* | C51: Registered Importer/Exporter Certificate Management | D51: WP7 | E51: S22 | F51: Registered Importer/Exporter Certificate | G51: 12 | H51: 53 | I51: =H51 -> 53 | J51: Deck slide 35 (marked * in serial.docx) | K51: N | L51: =INDEX(Inputs!$B$17:$B$19,MATCH(K51,Inputs!$A$17:$A$19,0)) -> 1 | M51: Y | N51: =IF(M51="Y",I51*L51,0) -> 53 | O51: =IF($N$53=0,0,N51/$N$53) -> 0.029297955 | P51: =O51*Inputs!$B$6 -> 3223946.9 | Q51: =P51/100000 -> 32.239469
A52: 21 | B52: Footnote* | C52: Registered Importer/Exporter Certificate Management – Renewal | D52: WP7 | E52: S23 | F52: Registered Importer/Exporter Renewal | G52: 12 | H52: 55 | I52: =H52 -> 55 | J52: Deck slide 36 (marked * in serial.docx) | K52: V | L52: =INDEX(Inputs!$B$17:$B$19,MATCH(K52,Inputs!$A$17:$A$19,0)) -> 0.5 | M52: Y | N52: =IF(M52="Y",I52*L52,0) -> 27.5 | O52: =IF($N$53=0,0,N52/$N$53) -> 0.015201769 | P52: =O52*Inputs!$B$6 -> 1672802.7 | Q52: =P52/100000 -> 16.728027
C53: TOTAL | I53: =SUM(I5:I52) -> 2378 | N53: =SUM(N5:N52) -> 1809 | O53: =SUM(O5:O52) -> 1 | P53: =SUM(P5:P52) -> 1.1004e+08 | Q53: =SUM(Q5:Q52) -> 1100.4
C54: Check: allocation equals development pool | P54: =IF(ABS(P53-Inputs!B6)<1,"OK","ERROR") -> OK
C55: Implied cost per work unit (BDT) | P55: =IF(N53=0,0,Inputs!B6/N53) -> 60829.187

Sheet Packages
A1: Approval packages (each ≤ 2 crore) and development time limits
A2: Packages follow the serial.docx priority. Each is approved, contracted and paid separately. Schedule inputs (blue) are months; dates are calendar month-ends. Time limit = go-live deadline in the work order.
A4: Package | B4: Scope | C4: Priorities (serial.docx) | D4: Work units | E4: Value by work share (BDT) | F4: Package value (BDT, excl. VAT) | G4: VAT & taxes (BDT) | H4: Value incl. VAT (BDT) | I4: Value incl. VAT (crore) | J4: Within 2-crore cap? | K4: Work start | L4: Design (m) | M4: Build (m) | N4: UAT (m) | O4: Go-live (m) | P4: Stabilisation (m) | Q4: Time limit to go-live (months) | R4: Approval needed by | S4: M1 Design sign-off | T4: M2 UAT acceptance | U4: M3 Go-live deadline | V4: M4 Stabilisation end | W4: Services in package
A5: WP0 | B5: Interim operation & maintenance of the 5 live services (Aug–Dec 2026), as proposed | C5: Live services | D5: — | E5: =Inputs!B5 -> 1625000 | F5: =Inputs!B5 -> 1625000 | G5: =F5*Inputs!$B$8 -> 243750 | H5: =F5+G5 -> 1868750 | I5: =H5/10000000 -> 0.186875 | J5: =IF(IF(Inputs!$B$9="Y",H5,F5)<=Inputs!$B$7,"OK","EXCEEDS") -> OK | K5: 46235 | L5: — | M5: — | N5: — | O5: — | P5: — | Q5: — | R5: 46387 | S5: — | T5: — | U5: 46387 | V5: — | W5: 5
A6: WP1 | B6: BSTI 2.0 transformation: common platform, HRM & Leave, Payroll, Standards (BDS) sale; Accounts | C6: 1–2 | D6: =SUMIF('Work Volume'!$D$5:$D$52,A6,'Work Volume'!$N$5:$N$52) -> 203.5 | E6: =SUMIF('Work Volume'!$D$5:$D$52,A6,'Work Volume'!$P$5:$P$52) -> 12378740 | F6: =ROUND(E6,Inputs!$B$14) -> 12379000 | G6: =F6*Inputs!$B$8 -> 1856850 | H6: =F6+G6 -> 14235850 | I6: =H6/10000000 -> 1.423585 | J6: =IF(IF(Inputs!$B$9="Y",H6,F6)<=Inputs!$B$7,"OK","EXCEEDS") -> OK | K6: 46388 | L6: 1 | M6: 3 | N6: 1 | O6: 1 | P6: 3 | Q6: =L6+M6+N6+O6 -> 6 | R6: =EOMONTH(K6,-2) -> 46356 | S6: =EOMONTH(K6,L6-1) -> 46418 | T6: =EOMONTH(K6,L6+M6+N6-1) -> 46538 | U6: =EOMONTH(K6,Q6-1) -> 46568 | V6: =EOMONTH(K6,Q6+P6-1) -> 46660 | W6: =COUNTIFS('Work Volume'!$D$5:$D$52,A6,'Work Volume'!$M$5:$M$52,"Y") -> 5
A7: WP2 | B7: CM licence services (non-scope & scope: new, renewal, brand inclusion) + common suspension / cancellation / withdrawal | C7: 3 | D7: =SUMIF('Work Volume'!$D$5:$D$52,A7,'Work Volume'!$N$5:$N$52) -> 265 | E7: =SUMIF('Work Volume'!$D$5:$D$52,A7,'Work Volume'!$P$5:$P$52) -> 16119735 | F7: =ROUND(E7,Inputs!$B$14) -> 16120000 | G7: =F7*Inputs!$B$8 -> 2418000 | H7: =F7+G7 -> 18538000 | I7: =H7/10000000 -> 1.8538 | J7: =IF(IF(Inputs!$B$9="Y",H7,F7)<=Inputs!$B$7,"OK","EXCEEDS") -> OK | K7: 46447 | L7: 2 | M7: 5 | N7: 1 | O7: 1 | P7: 3 | Q7: =L7+M7+N7+O7 -> 9 | R7: =EOMONTH(K7,-2) -> 46418 | S7: =EOMONTH(K7,L7-1) -> 46507 | T7: =EOMONTH(K7,L7+M7+N7-1) -> 46691 | U7: =EOMONTH(K7,Q7-1) -> 46721 | V7: =EOMONTH(K7,Q7+P7-1) -> 46812 | W7: =COUNTIFS('Work Volume'!$D$5:$D$52,A7,'Work Volume'!$M$5:$M$52,"Y") -> 7
A8: WP3 | B8: Laboratory testing (Chemical, Physical, Energy Meter) and PCR services | C8: 4–7 | D8: =SUMIF('Work Volume'!$D$5:$D$52,A8,'Work Volume'!$N$5:$N$52) -> 280.5 | E8: =SUMIF('Work Volume'!$D$5:$D$52,A8,'Work Volume'!$P$5:$P$52) -> 17062587 | F8: =ROUND(E8,Inputs!$B$14) -> 17063000 | G8: =F8*Inputs!$B$8 -> 2559450 | H8: =F8+G8 -> 19622450 | I8: =H8/10000000 -> 1.962245 | J8: =IF(IF(Inputs!$B$9="Y",H8,F8)<=Inputs!$B$7,"OK","EXCEEDS") -> OK | K8: 46419 | L8: 2 | M8: 6 | N8: 1 | O8: 1 | P8: 3 | Q8: =L8+M8+N8+O8 -> 10 | R8: =EOMONTH(K8,-2) -> 46387 | S8: =EOMONTH(K8,L8-1) -> 46477 | T8: =EOMONTH(K8,L8+M8+N8-1) -> 46691 | U8: =EOMONTH(K8,Q8-1) -> 46721 | V8: =EOMONTH(K8,Q8+P8-1) -> 46812 | W8: =COUNTIFS('Work Volume'!$D$5:$D$52,A8,'Work Volume'!$M$5:$M$52,"Y") -> 6
A9: WP4 | B9: Enforcement & field metrology: Mobile Court, Surveillance, Verification, Tank Calibration, Metrology Licence, Storage Tank Calibration | C9: 8–13 | D9: =SUMIF('Work Volume'!$D$5:$D$52,A9,'Work Volume'!$N$5:$N$52) -> 285 | E9: =SUMIF('Work Volume'!$D$5:$D$52,A9,'Work Volume'!$P$5:$P$52) -> 17336318 | F9: =ROUND(E9,Inputs!$B$14) -> 17336000 | G9: =F9*Inputs!$B$8 -> 2600400 | H9: =F9+G9 -> 19936400 | I9: =H9/10000000 -> 1.99364 | J9: =IF(IF(Inputs!$B$9="Y",H9,F9)<=Inputs!$B$7,"OK","EXCEEDS") -> OK | K9: 46844 | L9: 2 | M9: 5 | N9: 1 | O9: 1 | P9: 3 | Q9: =L9+M9+N9+O9 -> 9 | R9: =EOMONTH(K9,-2) -> 46812 | S9: =EOMONTH(K9,L9-1) -> 46904 | T9: =EOMONTH(K9,L9+M9+N9-1) -> 47087 | U9: =EOMONTH(K9,Q9-1) -> 47118 | V9: =EOMONTH(K9,Q9+P9-1) -> 47208 | W9: =COUNTIFS('Work Volume'!$D$5:$D$52,A9,'Work Volume'!$M$5:$M$52,"Y") -> 16
A10: WP5 | B10: MSC services (issue, renewal, scope inclusion) | C10: 14 | D10: =SUMIF('Work Volume'!$D$5:$D$52,A10,'Work Volume'!$N$5:$N$52) -> 267 | E10: =SUMIF('Work Volume'!$D$5:$D$52,A10,'Work Volume'!$P$5:$P$52) -> 16241393 | F10: =ROUND(E10,Inputs!$B$14) -> 16241000 | G10: =F10*Inputs!$B$8 -> 2436150 | H10: =F10+G10 -> 18677150 | I10: =H10/10000000 -> 1.867715 | J10: =IF(IF(Inputs!$B$9="Y",H10,F10)<=Inputs!$B$7,"OK","EXCEEDS") -> OK | K10: 47027 | L10: 2 | M10: 5 | N10: 1 | O10: 1 | P10: 3 | Q10: =L10+M10+N10+O10 -> 9 | R10: =EOMONTH(K10,-2) -> 46996 | S10: =EOMONTH(K10,L10-1) -> 47087 | T10: =EOMONTH(K10,L10+M10+N10-1) -> 47269 | U10: =EOMONTH(K10,Q10-1) -> 47299 | V10: =EOMONTH(K10,Q10+P10-1) -> 47391 | W10: =COUNTIFS('Work Volume'!$D$5:$D$52,A10,'Work Volume'!$M$5:$M$52,"Y") -> 3
A11: WP6 | B11: Halal certification, LPG / Fuel station registration, Case Management | C11: 15–17 | D11: =SUMIF('Work Volume'!$D$5:$D$52,A11,'Work Volume'!$N$5:$N$52) -> 285.5 | E11: =SUMIF('Work Volume'!$D$5:$D$52,A11,'Work Volume'!$P$5:$P$52) -> 17366733 | F11: =ROUND(E11,Inputs!$B$14) -> 17367000 | G11: =F11*Inputs!$B$8 -> 2605050 | H11: =F11+G11 -> 19972050 | I11: =H11/10000000 -> 1.997205 | J11: =IF(IF(Inputs!$B$9="Y",H11,F11)<=Inputs!$B$7,"OK","EXCEEDS") -> OK | K11: 47119 | L11: 2 | M11: 5 | N11: 1 | O11: 1 | P11: 3 | Q11: =L11+M11+N11+O11 -> 9 | R11: =EOMONTH(K11,-2) -> 47087 | S11: =EOMONTH(K11,L11-1) -> 47177 | T11: =EOMONTH(K11,L11+M11+N11-1) -> 47361 | U11: =EOMONTH(K11,Q11-1) -> 47391 | V11: =EOMONTH(K11,Q11+P11-1) -> 47483 | W11: =COUNTIFS('Work Volume'!$D$5:$D$52,A11,'Work Volume'!$M$5:$M$52,"Y") -> 6
A12: WP7 | B12: I&S Metrology Calibration (NML), Building measurement, BSW API integration, Importer/Exporter certificates* | C12: 18–21 | D12: =SUMIF('Work Volume'!$D$5:$D$52,A12,'Work Volume'!$N$5:$N$52) -> 222.5 | E12: =SUMIF('Work Volume'!$D$5:$D$52,A12,'Work Volume'!$P$5:$P$52) -> 13534494 | F12: =Inputs!$B$4-SUM(F5:F11) -> 13534000 | G12: =F12*Inputs!$B$8 -> 2030100 | H12: =F12+G12 -> 15564100 | I12: =H12/10000000 -> 1.55641 | J12: =IF(IF(Inputs!$B$9="Y",H12,F12)<=Inputs!$B$7,"OK","EXCEEDS") -> OK | K12: 47209 | L12: 2 | M12: 5 | N12: 1 | O12: 1 | P12: 3 | Q12: =L12+M12+N12+O12 -> 9 | R12: =EOMONTH(K12,-2) -> 47177 | S12: =EOMONTH(K12,L12-1) -> 47269 | T12: =EOMONTH(K12,L12+M12+N12-1) -> 47452 | U12: =EOMONTH(K12,Q12-1) -> 47483 | V12: =EOMONTH(K12,Q12+P12-1) -> 47573 | W12: =COUNTIFS('Work Volume'!$D$5:$D$52,A12,'Work Volume'!$M$5:$M$52,"Y") -> 5
B13: TOTAL ROLLOUT | D13: =SUM(D5:D12) -> 1809 | E13: =SUM(E5:E12) -> 1.11665e+08 | F13: =SUM(F5:F12) -> 111665000 | G13: =SUM(G5:G12) -> 16749750 | H13: =SUM(H5:H12) -> 128414750 | I13: =SUM(I5:I12) -> 12.841475 | U13: =MAX(U5:U12) -> 47483 | W13: =SUM(W5:W12) -> 53
B14: Check: package total equals rollout total in the proposal | F14: =IF(ABS(F13-Inputs!B4)<1,"OK","ERROR") -> OK
B15: Check: every included Work Volume row is assigned to a package | F15: =IF(ABS(D13-'Work Volume'!N53)<0.001,"OK","UNASSIGNED ROWS") -> OK
B16: Largest single approval (crore, incl. VAT) | F16: =MAX(I5:I12) -> 1.997205
B17: Overall development time limit: from first work start to last go-live (months) | F17: =(YEAR(U12)-YEAR(K6))*12+MONTH(U12)-MONTH(K6)+1 -> 36

Sheet Payment Schedule
A1: Milestone payment schedule
A2: Payment only on accepted milestones (see Inputs for acceptance evidence). Maintenance is unchanged from the proposal and approved in quarterly tranches.
A4: Phase | B4: Package | C4: Milestone | D4: % of package | E4: Due by | F4: Year | G4: Amount (BDT, excl. VAT) | H4: VAT & taxes (BDT) | I4: Amount incl. VAT (BDT)
A5: Rollout | B5: WP0 | C5: Interim O&M lump sum, Aug–Dec 2026 | D5: 1 | E5: =Packages!U5 -> 46387 | F5: =YEAR(E5) -> 2026 | G5: =D5*Packages!F5 -> 1625000 | H5: =G5*Inputs!$B$8 -> 243750 | I5: =G5+H5 -> 1868750
A6: Rollout | B6: WP1 | C6: =Inputs!A23 -> M1 Design & prototype sign-off | D6: =Inputs!B23 -> 0.2 | E6: =Packages!S6 -> 46418 | F6: =YEAR(E6) -> 2027 | G6: =D6*Packages!$F$6 -> 2475800 | H6: =G6*Inputs!$B$8 -> 371370 | I6: =G6+H6 -> 2847170
A7: Rollout | B7: WP1 | C7: =Inputs!A24 -> M2 UAT acceptance | D7: =Inputs!B24 -> 0.3 | E7: =Packages!T6 -> 46538 | F7: =YEAR(E7) -> 2027 | G7: =D7*Packages!$F$6 -> 3713700 | H7: =G7*Inputs!$B$8 -> 557055 | I7: =G7+H7 -> 4270755
A8: Rollout | B8: WP1 | C8: =Inputs!A25 -> M3 Go-live | D8: =Inputs!B25 -> 0.4 | E8: =Packages!U6 -> 46568 | F8: =YEAR(E8) -> 2027 | G8: =D8*Packages!$F$6 -> 4951600 | H8: =G8*Inputs!$B$8 -> 742740 | I8: =G8+H8 -> 5694340
A9: Rollout | B9: WP1 | C9: =Inputs!A26 -> M4 End of stabilisation | D9: =Inputs!B26 -> 0.1 | E9: =Packages!V6 -> 46660 | F9: =YEAR(E9) -> 2027 | G9: =D9*Packages!$F$6 -> 1237900 | H9: =G9*Inputs!$B$8 -> 185685 | I9: =G9+H9 -> 1423585
A10: Rollout | B10: WP2 | C10: =Inputs!A23 -> M1 Design & prototype sign-off | D10: =Inputs!B23 -> 0.2 | E10: =Packages!S7 -> 46507 | F10: =YEAR(E10) -> 2027 | G10: =D10*Packages!$F$7 -> 3224000 | H10: =G10*Inputs!$B$8 -> 483600 | I10: =G10+H10 -> 3707600
A11: Rollout | B11: WP2 | C11: =Inputs!A24 -> M2 UAT acceptance | D11: =Inputs!B24 -> 0.3 | E11: =Packages!T7 -> 46691 | F11: =YEAR(E11) -> 2027 | G11: =D11*Packages!$F$7 -> 4836000 | H11: =G11*Inputs!$B$8 -> 725400 | I11: =G11+H11 -> 5561400
A12: Rollout | B12: WP2 | C12: =Inputs!A25 -> M3 Go-live | D12: =Inputs!B25 -> 0.4 | E12: =Packages!U7 -> 46721 | F12: =YEAR(E12) -> 2027 | G12: =D12*Packages!$F$7 -> 6448000 | H12: =G12*Inputs!$B$8 -> 967200 | I12: =G12+H12 -> 7415200
A13: Rollout | B13: WP2 | C13: =Inputs!A26 -> M4 End of stabilisation | D13: =Inputs!B26 -> 0.1 | E13: =Packages!V7 -> 46812 | F13: =YEAR(E13) -> 2028 | G13: =D13*Packages!$F$7 -> 1612000 | H13: =G13*Inputs!$B$8 -> 241800 | I13: =G13+H13 -> 1853800
A14: Rollout | B14: WP3 | C14: =Inputs!A23 -> M1 Design & prototype sign-off | D14: =Inputs!B23 -> 0.2 | E14: =Packages!S8 -> 46477 | F14: =YEAR(E14) -> 2027 | G14: =D14*Packages!$F$8 -> 3412600 | H14: =G14*Inputs!$B$8 -> 511890 | I14: =G14+H14 -> 3924490
A15: Rollout | B15: WP3 | C15: =Inputs!A24 -> M2 UAT acceptance | D15: =Inputs!B24 -> 0.3 | E15: =Packages!T8 -> 46691 | F15: =YEAR(E15) -> 2027 | G15: =D15*Packages!$F$8 -> 5118900 | H15: =G15*Inputs!$B$8 -> 767835 | I15: =G15+H15 -> 5886735
A16: Rollout | B16: WP3 | C16: =Inputs!A25 -> M3 Go-live | D16: =Inputs!B25 -> 0.4 | E16: =Packages!U8 -> 46721 | F16: =YEAR(E16) -> 2027 | G16: =D16*Packages!$F$8 -> 6825200 | H16: =G16*Inputs!$B$8 -> 1023780 | I16: =G16+H16 -> 7848980
A17: Rollout | B17: WP3 | C17: =Inputs!A26 -> M4 End of stabilisation | D17: =Inputs!B26 -> 0.1 | E17: =Packages!V8 -> 46812 | F17: =YEAR(E17) -> 2028 | G17: =D17*Packages!$F$8 -> 1706300 | H17: =G17*Inputs!$B$8 -> 255945 | I17: =G17+H17 -> 1962245
A18: Rollout | B18: WP4 | C18: =Inputs!A23 -> M1 Design & prototype sign-off | D18: =Inputs!B23 -> 0.2 | E18: =Packages!S9 -> 46904 | F18: =YEAR(E18) -> 2028 | G18: =D18*Packages!$F$9 -> 3467200 | H18: =G18*Inputs!$B$8 -> 520080 | I18: =G18+H18 -> 3987280
A19: Rollout | B19: WP4 | C19: =Inputs!A24 -> M2 UAT acceptance | D19: =Inputs!B24 -> 0.3 | E19: =Packages!T9 -> 47087 | F19: =YEAR(E19) -> 2028 | G19: =D19*Packages!$F$9 -> 5200800 | H19: =G19*Inputs!$B$8 -> 780120 | I19: =G19+H19 -> 5980920
A20: Rollout | B20: WP4 | C20: =Inputs!A25 -> M3 Go-live | D20: =Inputs!B25 -> 0.4 | E20: =Packages!U9 -> 47118 | F20: =YEAR(E20) -> 2028 | G20: =D20*Packages!$F$9 -> 6934400 | H20: =G20*Inputs!$B$8 -> 1040160 | I20: =G20+H20 -> 7974560
A21: Rollout | B21: WP4 | C21: =Inputs!A26 -> M4 End of stabilisation | D21: =Inputs!B26 -> 0.1 | E21: =Packages!V9 -> 47208 | F21: =YEAR(E21) -> 2029 | G21: =D21*Packages!$F$9 -> 1733600 | H21: =G21*Inputs!$B$8 -> 260040 | I21: =G21+H21 -> 1993640
A22: Rollout | B22: WP5 | C22: =Inputs!A23 -> M1 Design & prototype sign-off | D22: =Inputs!B23 -> 0.2 | E22: =Packages!S10 -> 47087 | F22: =YEAR(E22) -> 2028 | G22: =D22*Packages!$F$10 -> 3248200 | H22: =G22*Inputs!$B$8 -> 487230 | I22: =G22+H22 -> 3735430
A23: Rollout | B23: WP5 | C23: =Inputs!A24 -> M2 UAT acceptance | D23: =Inputs!B24 -> 0.3 | E23: =Packages!T10 -> 47269 | F23: =YEAR(E23) -> 2029 | G23: =D23*Packages!$F$10 -> 4872300 | H23: =G23*Inputs!$B$8 -> 730845 | I23: =G23+H23 -> 5603145
A24: Rollout | B24: WP5 | C24: =Inputs!A25 -> M3 Go-live | D24: =Inputs!B25 -> 0.4 | E24: =Packages!U10 -> 47299 | F24: =YEAR(E24) -> 2029 | G24: =D24*Packages!$F$10 -> 6496400 | H24: =G24*Inputs!$B$8 -> 974460 | I24: =G24+H24 -> 7470860
A25: Rollout | B25: WP5 | C25: =Inputs!A26 -> M4 End of stabilisation | D25: =Inputs!B26 -> 0.1 | E25: =Packages!V10 -> 47391 | F25: =YEAR(E25) -> 2029 | G25: =D25*Packages!$F$10 -> 1624100 | H25: =G25*Inputs!$B$8 -> 243615 | I25: =G25+H25 -> 1867715
A26: Rollout | B26: WP6 | C26: =Inputs!A23 -> M1 Design & prototype sign-off | D26: =Inputs!B23 -> 0.2 | E26: =Packages!S11 -> 47177 | F26: =YEAR(E26) -> 2029 | G26: =D26*Packages!$F$11 -> 3473400 | H26: =G26*Inputs!$B$8 -> 521010 | I26: =G26+H26 -> 3994410
A27: Rollout | B27: WP6 | C27: =Inputs!A24 -> M2 UAT acceptance | D27: =Inputs!B24 -> 0.3 | E27: =Packages!T11 -> 47361 | F27: =YEAR(E27) -> 2029 | G27: =D27*Packages!$F$11 -> 5210100 | H27: =G27*Inputs!$B$8 -> 781515 | I27: =G27+H27 -> 5991615
A28: Rollout | B28: WP6 | C28: =Inputs!A25 -> M3 Go-live | D28: =Inputs!B25 -> 0.4 | E28: =Packages!U11 -> 47391 | F28: =YEAR(E28) -> 2029 | G28: =D28*Packages!$F$11 -> 6946800 | H28: =G28*Inputs!$B$8 -> 1042020 | I28: =G28+H28 -> 7988820
A29: Rollout | B29: WP6 | C29: =Inputs!A26 -> M4 End of stabilisation | D29: =Inputs!B26 -> 0.1 | E29: =Packages!V11 -> 47483 | F29: =YEAR(E29) -> 2029 | G29: =D29*Packages!$F$11 -> 1736700 | H29: =G29*Inputs!$B$8 -> 260505 | I29: =G29+H29 -> 1997205
A30: Rollout | B30: WP7 | C30: =Inputs!A23 -> M1 Design & prototype sign-off | D30: =Inputs!B23 -> 0.2 | E30: =Packages!S12 -> 47269 | F30: =YEAR(E30) -> 2029 | G30: =D30*Packages!$F$12 -> 2706800 | H30: =G30*Inputs!$B$8 -> 406020 | I30: =G30+H30 -> 3112820
A31: Rollout | B31: WP7 | C31: =Inputs!A24 -> M2 UAT acceptance | D31: =Inputs!B24 -> 0.3 | E31: =Packages!T12 -> 47452 | F31: =YEAR(E31) -> 2029 | G31: =D31*Packages!$F$12 -> 4060200 | H31: =G31*Inputs!$B$8 -> 609030 | I31: =G31+H31 -> 4669230
A32: Rollout | B32: WP7 | C32: =Inputs!A25 -> M3 Go-live | D32: =Inputs!B25 -> 0.4 | E32: =Packages!U12 -> 47483 | F32: =YEAR(E32) -> 2029 | G32: =D32*Packages!$F$12 -> 5413600 | H32: =G32*Inputs!$B$8 -> 812040 | I32: =G32+H32 -> 6225640
A33: Rollout | B33: WP7 | C33: =Inputs!A26 -> M4 End of stabilisation | D33: =Inputs!B26 -> 0.1 | E33: =Packages!V12 -> 47573 | F33: =YEAR(E33) -> 2030 | G33: =D33*Packages!$F$12 -> 1353400 | H33: =G33*Inputs!$B$8 -> 203010 | I33: =G33+H33 -> 1556410
A34: Maintenance | B34: MNT | C34: ="Maintenance tranche 1 (" & Inputs!$B$12 & " months, 33 services)" -> Maintenance tranche 1 (3 months, 33 services) | D34: =Inputs!$B$12/Inputs!$B$11 -> 0.125 | E34: =EOMONTH(Inputs!$B$13,0*Inputs!$B$12+Inputs!$B$12-1) -> 47573 | F34: =YEAR(E34) -> 2030 | G34: =IF(0*Inputs!$B$12<Inputs!$B$11,D34*Inputs!$B$10,0) -> 9405000 | H34: =G34*Inputs!$B$8 -> 1410750 | I34: =G34+H34 -> 10815750
A35: Maintenance | B35: MNT | C35: ="Maintenance tranche 2 (" & Inputs!$B$12 & " months, 33 services)" -> Maintenance tranche 2 (3 months, 33 services) | D35: =Inputs!$B$12/Inputs!$B$11 -> 0.125 | E35: =EOMONTH(Inputs!$B$13,1*Inputs!$B$12+Inputs!$B$12-1) -> 47664 | F35: =YEAR(E35) -> 2030 | G35: =IF(1*Inputs!$B$12<Inputs!$B$11,D35*Inputs!$B$10,0) -> 9405000 | H35: =G35*Inputs!$B$8 -> 1410750 | I35: =G35+H35 -> 10815750
A36: Maintenance | B36: MNT | C36: ="Maintenance tranche 3 (" & Inputs!$B$12 & " months, 33 services)" -> Maintenance tranche 3 (3 months, 33 services) | D36: =Inputs!$B$12/Inputs!$B$11 -> 0.125 | E36: =EOMONTH(Inputs!$B$13,2*Inputs!$B$12+Inputs!$B$12-1) -> 47756 | F36: =YEAR(E36) -> 2030 | G36: =IF(2*Inputs!$B$12<Inputs!$B$11,D36*Inputs!$B$10,0) -> 9405000 | H36: =G36*Inputs!$B$8 -> 1410750 | I36: =G36+H36 -> 10815750
A37: Maintenance | B37: MNT | C37: ="Maintenance tranche 4 (" & Inputs!$B$12 & " months, 33 services)" -> Maintenance tranche 4 (3 months, 33 services) | D37: =Inputs!$B$12/Inputs!$B$11 -> 0.125 | E37: =EOMONTH(Inputs!$B$13,3*Inputs!$B$12+Inputs!$B$12-1) -> 47848 | F37: =YEAR(E37) -> 2030 | G37: =IF(3*Inputs!$B$12<Inputs!$B$11,D37*Inputs!$B$10,0) -> 9405000 | H37: =G37*Inputs!$B$8 -> 1410750 | I37: =G37+H37 -> 10815750
A38: Maintenance | B38: MNT | C38: ="Maintenance tranche 5 (" & Inputs!$B$12 & " months, 33 services)" -> Maintenance tranche 5 (3 months, 33 services) | D38: =Inputs!$B$12/Inputs!$B$11 -> 0.125 | E38: =EOMONTH(Inputs!$B$13,4*Inputs!$B$12+Inputs!$B$12-1) -> 47938 | F38: =YEAR(E38) -> 2031 | G38: =IF(4*Inputs!$B$12<Inputs!$B$11,D38*Inputs!$B$10,0) -> 9405000 | H38: =G38*Inputs!$B$8 -> 1410750 | I38: =G38+H38 -> 10815750
A39: Maintenance | B39: MNT | C39: ="Maintenance tranche 6 (" & Inputs!$B$12 & " months, 33 services)" -> Maintenance tranche 6 (3 months, 33 services) | D39: =Inputs!$B$12/Inputs!$B$11 -> 0.125 | E39: =EOMONTH(Inputs!$B$13,5*Inputs!$B$12+Inputs!$B$12-1) -> 48029 | F39: =YEAR(E39) -> 2031 | G39: =IF(5*Inputs!$B$12<Inputs!$B$11,D39*Inputs!$B$10,0) -> 9405000 | H39: =G39*Inputs!$B$8 -> 1410750 | I39: =G39+H39 -> 10815750
A40: Maintenance | B40: MNT | C40: ="Maintenance tranche 7 (" & Inputs!$B$12 & " months, 33 services)" -> Maintenance tranche 7 (3 months, 33 services) | D40: =Inputs!$B$12/Inputs!$B$11 -> 0.125 | E40: =EOMONTH(Inputs!$B$13,6*Inputs!$B$12+Inputs!$B$12-1) -> 48121 | F40: =YEAR(E40) -> 2031 | G40: =IF(6*Inputs!$B$12<Inputs!$B$11,D40*Inputs!$B$10,0) -> 9405000 | H40: =G40*Inputs!$B$8 -> 1410750 | I40: =G40+H40 -> 10815750
A41: Maintenance | B41: MNT | C41: ="Maintenance tranche 8 (" & Inputs!$B$12 & " months, 33 services)" -> Maintenance tranche 8 (3 months, 33 services) | D41: =Inputs!$B$12/Inputs!$B$11 -> 0.125 | E41: =EOMONTH(Inputs!$B$13,7*Inputs!$B$12+Inputs!$B$12-1) -> 48213 | F41: =YEAR(E41) -> 2031 | G41: =IF(7*Inputs!$B$12<Inputs!$B$11,D41*Inputs!$B$10,0) -> 9405000 | H41: =G41*Inputs!$B$8 -> 1410750 | I41: =G41+H41 -> 10815750
C42: TOTAL | G42: =SUM(G5:G41) -> 186905000 | H42: =SUM(H5:H41) -> 28035750 | I42: =SUM(I5:I41) -> 214940750
C43: Rollout subtotal | G43: =SUMIF(A5:A41,"Rollout",G5:G41) -> 111665000
C44: Maintenance subtotal | G44: =SUMIF(A5:A41,"Maintenance",G5:G41) -> 75240000
C45: Check: rollout payments = rollout total; maintenance = proposal | G45: =IF(AND(ABS(G43-Inputs!B4)<1,ABS(G44-Inputs!B10)<1),"OK","ERROR") -> OK
C46: Check: each maintenance tranche within the cap | G46: =IF(IF(Inputs!$B$9="Y",MAX(I34:I41),MAX(G34:G41))<=Inputs!B7,"OK","EXCEEDS") -> OK

Sheet Original Offer
A1: OrangeBD offer as submitted (Financial Proposal V4), for comparison
A2: Source: BSTI 2.0 - Financial Proposal V4.pdf, pages 4–5. Inputs typed from the PDF; payments recomputed by formula.
A4: Period | B4: Year | C4: Live services | D4: Rate / service / month (BDT) | E4: Months | F4: Payment (BDT)
A5: Aug–Dec 2026 | B5: 2026 | C5: 5 | D5: 65000 | E5: 5 | F5: =C5*D5*E5 -> 1625000
A6: Jan–Mar 2027 | B6: 2027 | C6: 5 | D6: 180000 | E6: 3 | F6: =C6*D6*E6 -> 2700000
A7: Apr–Jun 2027 | B7: 2027 | C7: 8 | D7: 180000 | E7: 3 | F7: =C7*D7*E7 -> 4320000
A8: Jul–Sep 2027 | B8: 2027 | C8: 11 | D8: 180000 | E8: 3 | F8: =C8*D8*E8 -> 5940000
A9: Oct–Dec 2027 | B9: 2027 | C9: 14 | D9: 180000 | E9: 3 | F9: =C9*D9*E9 -> 7560000
A10: Jan–Mar 2028 | B10: 2028 | C10: 17 | D10: 155000 | E10: 3 | F10: =C10*D10*E10 -> 7905000
A11: Apr–Jun 2028 | B11: 2028 | C11: 20 | D11: 155000 | E11: 3 | F11: =C11*D11*E11 -> 9300000
A12: Jul–Sep 2028 | B12: 2028 | C12: 23 | D12: 155000 | E12: 3 | F12: =C12*D12*E12 -> 10695000
A13: Oct–Dec 2028 | B13: 2028 | C13: 26 | D13: 155000 | E13: 3 | F13: =C13*D13*E13 -> 12090000
A14: Jan–Mar 2029 | B14: 2029 | C14: 29 | D14: 130000 | E14: 3 | F14: =C14*D14*E14 -> 11310000
A15: Apr–Jun 2029 | B15: 2029 | C15: 32 | D15: 130000 | E15: 3 | F15: =C15*D15*E15 -> 12480000
A16: Jul–Sep 2029 | B16: 2029 | C16: 33 | D16: 130000 | E16: 3 | F16: =C16*D16*E16 -> 12870000
... A19: 2031 (maintenance) | B19: 2031 | C19: 33 | D19: 95000 | E19: 12 | F19: =C19*D19*E19 -> 37620000
A20: Rollout total | F20: =SUM(F5:F17) -> 111665000
A21: Maintenance total | F21: =SUM(F18:F19) -> 75240000
A22: Grand total | F22: =F20+F21 -> 186905000
A23: Check vs proposal (11,16,65,000 / 7,52,40,000) | F23: =IF(AND(F20=Inputs!B4,F21=Inputs!B10),"OK","ERROR") -> OK

Sheet Gantt
A1: Development schedule (month by month)
A2: D = design & prototype · B = build · U = UAT · G = go-live (deadline at month-end) · S = stabilisation / warranty. Driven by the schedule inputs on Packages.
A4: Package | B4: Scope | C4: 46388 | D4: 46419 | E4: 46447 | F4: 46478 | G4: 46508 | H4: 46539 | I4: 46569 | J4: 46600 | K4: 46631 | L4: 46661 | M4: 46692 | N4: 46722 | O4: 46753 | P4: 46784 | Q4: 46813 | R4: 46844 | S4: 46874 | T4: 46905 | U4: 46935 | V4: 46966 | W4: 46997 | X4: 47027 | Y4: 47058 | Z4: 47088 | AA4: 47119 | AB4: 47150 | AC4: 47178 | AD4: 47209 | AE4: 47239 | AF4: 47270 | AG4: 47300 | AH4: 47331 | AI4: 47362 | AJ4: 47392 | AK4: 47423 | AL4: 47453 | AM4: 47484 | AN4: 47515 | AO4: 47543
A5: =Packages!A6 -> WP1 | B5: =Packages!B6 -> BSTI 2.0 transformation: common platform, HRM & Leave, Payroll, Standards (BDS) sale; Accounts | C5: =IF(C$4<Packages!$K$6,"",IF(C$4<=EOMONTH(Packages!$K$6,Packages!$L$6-1),"D",IF(C$4<=EOMONTH(Packages!$K$6,Packages!$L$6+Packages!$M$6-1),"B",IF(C$4<=EOMONTH(Packages!$K$6,Packages!$L$6+Packages!$M$6+Packages!$N$6-1),"U",IF(C$4<=EOMONTH(Packages!$K$6,Packages!$L$6+Packages!$M$6+Packages!$N$6+Packages!$O$6-1),"G",IF(C$4<=EOMONTH(Packages!$K$6,Packages!$L$6+Packages!$M$6+Packages!$N$6+Packages!$O$6+Packages!$P$6-1),"S","")))))) -> D | D5: =IF(D$4<Packages!$K$6,"",IF(D$4<=EOMONTH(Packages!$K$6,Packages!$L$6-1),"D",IF(D$4<=EOMONTH(Packages!$K$6,Packages!$L$6+Packages!$M$6-1),"B",IF(D$4<=EOMONTH(Packages!$K$6,Packages!$L$6+Packages!$M$6+Packages!$N$6-1),"U",IF(D$4<=EOMONTH(Packages!$K$6,Packages!$L$6+Packages!$M$6+Packages!$N$6+Packages!$O$6-1),"G",IF(D$4<=EOMONTH(Packages!$K$6,Packages!$L$6+Packages!$M$6+Packages!$N$6+Packages!$O$6+Packages!$P$6-1),"S","")))))) -> B | E5: =IF(E$4<Packages!$K$6,"",IF(E$4<=EOMONTH(Packages!$K$6,Packages!$L$6-1),"D",IF(E$4<=EOMONTH(Packages!$K$6,Packages!$L$6+Packages!$M$6-1),"B",IF(E$4<=EOMONTH(Packages!$K$6,Packages!$L$6+Packages!$M$6+Packages!$N$6-1),"U",IF(E$4<=EOMONTH(Packages!$K$6,Packages!$L$6+Packages!$M$6+Packages!$N$6+Packages!$O$6-1),"G",IF(E$4<=EOMONTH(Packages!$K$6,Packages!$L$6+Packages!$M$6+Packages!$N$6+Packages!$O$6+Packages!$P$6-1),"S","")))))) -> B | F5: =IF(F$4<Packages!$K$6,"",IF(F$4<=EOMONTH(Packages!$K$6,Packages!$L$6-1),"D",IF(F$4<=EOMONTH(Packages!$K$6,Packages!$L$6+Packages!$M$6-1),"B",IF(F$4<=EOMONTH(Packages!$K$6,Packages!$L$6+Packages!$M$6+Packages!$N$6-1),"U",IF(F$4<=EOMONTH(Packages!$K$6,Packages!$L$6+Packages!$M$6+Packages!$N$6+Packages!$O$6-1),"G",IF(F$4<=EOMONTH(Packages!$K$6,Packages!$L$6+Packages!$M$6+Packages!$N$6+Packages!$O$6+Packages!$P$6-1),"S","")))))) -> B | G5: =IF(G$4<Packages!$K$6,"",IF(G$4<=EOMONTH(Packages!$K$6,Packages!$L$6-1),"D",IF(G$4<=EOMONTH(Packages!$K$6,Packages!$L$6+Packages!$M$6-1),"B",IF(G$4<=EOMONTH(Packages!$K$6,Packages!$L$6+Packages!$M$6+Packages!$N$6-1),"U",IF(G$4<=EOMONTH(Packages!$K$6,Packages!$L$6+Packages!$M$6+Packages!$N$6+Packages!$O$6-1),"G",IF(G$4<=EOMONTH(Packages!$K$6,Packages!$L$6+Packages!$M$6+Packages!$N$6+Packages!$O$6+Packages!$P$6-1),"S","")))))) -> U | H5: =IF(H$4<Packages!$K$6,"",IF(H$4<=EOMONTH(Packages!$K$6,Packages!$L$6-1),"D",IF(H$4<=EOMONTH(Packages!$K$6,Packages!$L$6+Packages!$M$6-1),"B",IF(H$4<=EOMONTH(Packages!$K$6,Packages!$L$6+Packages!$M$6+Packages!$N$6-1),"U",IF(H$4<=EOMONTH(Packages!$K$6,Packages!$L$6+Packages!$M$6+Packages!$N$6+Packages!$O$6-1),"G",IF(H$4<=EOMONTH(Packages!$K$6,Packages!$L$6+Packages!$M$6+Packages!$N$6+Packages!$O$6+Packages!$P$6-1),"S","")))))) -> G | I5: =IF(I$4<Packages!$K$6,"",IF(I$4<=EOMONTH(Packages!$K$6,Packages!$L$6-1),"D",IF(I$4<=EOMONTH(Packages!$K$6,Packages!$L$6+Packages!$M$6-1),"B",IF(I$4<=EOMONTH(Packages!$K$6,Packages!$L$6+Packages!$M$6+Packages!$N$6-1),"U",IF(I$4<=EOMONTH(Packages!$K$6,Packages!$L$6+Packages!$M$6+Packages!$N$6+Packages!$O$6-1),"G",IF(I$4<=EOMONTH(Packages!$K$6,Packages!$L$6+Packages!$M$6+Packages!$N$6+Packages!$O$6+Packages!$P$6-1),"S","")))))) -> S | J5: =IF(J$4<Packages!$K$6,"",IF(J$4<=EOMONTH(Packages!$K$6,Packages!$L$6-1),"D",IF(J$4<=EOMONTH(Packages!$K$6,Packages!$L$6+Packages!$M$6-1),"B",IF(J$4<=EOMONTH(Packages!$K$6,Packages!$L$6+Packages!$M$6+Packages!$N$6-1),"U",IF(J$4<=EOMONTH(Packages!$K$6,Packages!$L$6+Packages!$M$6+Packages!$N$6+Packages!$O$6-1),"G",IF(J$4<=EOMONTH(Packages!$K$6,Packages!$L$6+Packages!$M$6+Packages!$N$6+Packages!$O$6+Packages!$P$6-1),"S","")))))) -> S | ... AO5: =IF(AO$4<Packages!$K$6,"",IF(AO$4<=EOMONTH(Packages!$K$6,Packages!$L$6-1),"D",IF(AO$4<=EOMONTH(Packages!$K$6,Packages!$L$6+Packages!$M$6-1),"B",IF(AO$4<=EOMONTH(Packages!$K$6,Packages!$L$6+Packages!$M$6+Packages!$N$6-1),"U",IF(AO$4<=EOMONTH(Packages!$K$6,Packages!$L$6+Packages!$M$6+Packages!$N$6+Packages!$O$6-1),"G",IF(AO$4<=EOMONTH(Packages!$K$6,Packages!$L$6+Packages!$M$6+Packages!$N$6+Packages!$O$6+Packages!$P$6-1),"S",""))))))
A6: =Packages!A7 -> WP2 | B6: =Packages!B7 -> CM licence services (non-scope & scope: new, renewal, brand inclusion) + common suspension / cancellation / withdrawal | C6: =IF(C$4<Packages!$K$7,"",IF(C$4<=EOMONTH(Packages!$K$7,Packages!$L$7-1),"D",IF(C$4<=EOMONTH(Packages!$K$7,Packages!$L$7+Packages!$M$7-1),"B",IF(C$4<=EOMONTH(Packages!$K$7,Packages!$L$7+Packages!$M$7+Packages!$N$7-1),"U",IF(C$4<=EOMONTH(Packages!$K$7,Packages!$L$7+Packages!$M$7+Packages!$N$7+Packages!$O$7-1),"G",IF(C$4<=EOMONTH(Packages!$K$7,Packages!$L$7+Packages!$M$7+Packages!$N$7+Packages!$O$7+Packages!$P$7-1),"S","")))))) | D6: =IF(D$4<Packages!$K$7,"",IF(D$4<=EOMONTH(Packages!$K$7,Packages!$L$7-1),"D",IF(D$4<=EOMONTH(Packages!$K$7,Packages!$L$7+Packages!$M$7-1),"B",IF(D$4<=EOMONTH(Packages!$K$7,Packages!$L$7+Packages!$M$7+Packages!$N$7-1),"U",IF(D$4<=EOMONTH(Packages!$K$7,Packages!$L$7+Packages!$M$7+Packages!$N$7+Packages!$O$7-1),"G",IF(D$4<=EOMONTH(Packages!$K$7,Packages!$L$7+Packages!$M$7+Packages!$N$7+Packages!$O$7+Packages!$P$7-1),"S","")))))) | E6: =IF(E$4<Packages!$K$7,"",IF(E$4<=EOMONTH(Packages!$K$7,Packages!$L$7-1),"D",IF(E$4<=EOMONTH(Packages!$K$7,Packages!$L$7+Packages!$M$7-1),"B",IF(E$4<=EOMONTH(Packages!$K$7,Packages!$L$7+Packages!$M$7+Packages!$N$7-1),"U",IF(E$4<=EOMONTH(Packages!$K$7,Packages!$L$7+Packages!$M$7+Packages!$N$7+Packages!$O$7-1),"G",IF(E$4<=EOMONTH(Packages!$K$7,Packages!$L$7+Packages!$M$7+Packages!$N$7+Packages!$O$7+Packages!$P$7-1),"S","")))))) -> D | F6: =IF(F$4<Packages!$K$7,"",IF(F$4<=EOMONTH(Packages!$K$7,Packages!$L$7-1),"D",IF(F$4<=EOMONTH(Packages!$K$7,Packages!$L$7+Packages!$M$7-1),"B",IF(F$4<=EOMONTH(Packages!$K$7,Packages!$L$7+Packages!$M$7+Packages!$N$7-1),"U",IF(F$4<=EOMONTH(Packages!$K$7,Packages!$L$7+Packages!$M$7+Packages!$N$7+Packages!$O$7-1),"G",IF(F$4<=EOMONTH(Packages!$K$7,Packages!$L$7+Packages!$M$7+Packages!$N$7+Packages!$O$7+Packages!$P$7-1),"S","")))))) -> D | G6: =IF(G$4<Packages!$K$7,"",IF(G$4<=EOMONTH(Packages!$K$7,Packages!$L$7-1),"D",IF(G$4<=EOMONTH(Packages!$K$7,Packages!$L$7+Packages!$M$7-1),"B",IF(G$4<=EOMONTH(Packages!$K$7,Packages!$L$7+Packages!$M$7+Packages!$N$7-1),"U",IF(G$4<=EOMONTH(Packages!$K$7,Packages!$L$7+Packages!$M$7+Packages!$N$7+Packages!$O$7-1),"G",IF(G$4<=EOMONTH(Packages!$K$7,Packages!$L$7+Packages!$M$7+Packages!$N$7+Packages!$O$7+Packages!$P$7-1),"S","")))))) -> B | H6: =IF(H$4<Packages!$K$7,"",IF(H$4<=EOMONTH(Packages!$K$7,Packages!$L$7-1),"D",IF(H$4<=EOMONTH(Packages!$K$7,Packages!$L$7+Packages!$M$7-1),"B",IF(H$4<=EOMONTH(Packages!$K$7,Packages!$L$7+Packages!$M$7+Packages!$N$7-1),"U",IF(H$4<=EOMONTH(Packages!$K$7,Packages!$L$7+Packages!$M$7+Packages!$N$7+Packages!$O$7-1),"G",IF(H$4<=EOMONTH(Packages!$K$7,Packages!$L$7+Packages!$M$7+Packages!$N$7+Packages!$O$7+Packages!$P$7-1),"S","")))))) -> B | I6: =IF(I$4<Packages!$K$7,"",IF(I$4<=EOMONTH(Packages!$K$7,Packages!$L$7-1),"D",IF(I$4<=EOMONTH(Packages!$K$7,Packages!$L$7+Packages!$M$7-1),"B",IF(I$4<=EOMONTH(Packages!$K$7,Packages!$L$7+Packages!$M$7+Packages!$N$7-1),"U",IF(I$4<=EOMONTH(Packages!$K$7,Packages!$L$7+Packages!$M$7+Packages!$N$7+Packages!$O$7-1),"G",IF(I$4<=EOMONTH(Packages!$K$7,Packages!$L$7+Packages!$M$7+Packages!$N$7+Packages!$O$7+Packages!$P$7-1),"S","")))))) -> B | J6: =IF(J$4<Packages!$K$7,"",IF(J$4<=EOMONTH(Packages!$K$7,Packages!$L$7-1),"D",IF(J$4<=EOMONTH(Packages!$K$7,Packages!$L$7+Packages!$M$7-1),"B",IF(J$4<=EOMONTH(Packages!$K$7,Packages!$L$7+Packages!$M$7+Packages!$N$7-1),"U",IF(J$4<=EOMONTH(Packages!$K$7,Packages!$L$7+Packages!$M$7+Packages!$N$7+Packages!$O$7-1),"G",IF(J$4<=EOMONTH(Packages!$K$7,Packages!$L$7+Packages!$M$7+Packages!$N$7+Packages!$O$7+Packages!$P$7-1),"S","")))))) -> B | ... AO6: =IF(AO$4<Packages!$K$7,"",IF(AO$4<=EOMONTH(Packages!$K$7,Packages!$L$7-1),"D",IF(AO$4<=EOMONTH(Packages!$K$7,Packages!$L$7+Packages!$M$7-1),"B",IF(AO$4<=EOMONTH(Packages!$K$7,Packages!$L$7+Packages!$M$7+Packages!$N$7-1),"U",IF(AO$4<=EOMONTH(Packages!$K$7,Packages!$L$7+Packages!$M$7+Packages!$N$7+Packages!$O$7-1),"G",IF(AO$4<=EOMONTH(Packages!$K$7,Packages!$L$7+Packages!$M$7+Packages!$N$7+Packages!$O$7+Packages!$P$7-1),"S",""))))))
A7: =Packages!A8 -> WP3 | B7: =Packages!B8 -> Laboratory testing (Chemical, Physical, Energy Meter) and PCR services | C7: =IF(C$4<Packages!$K$8,"",IF(C$4<=EOMONTH(Packages!$K$8,Packages!$L$8-1),"D",IF(C$4<=EOMONTH(Packages!$K$8,Packages!$L$8+Packages!$M$8-1),"B",IF(C$4<=EOMONTH(Packages!$K$8,Packages!$L$8+Packages!$M$8+Packages!$N$8-1),"U",IF(C$4<=EOMONTH(Packages!$K$8,Packages!$L$8+Packages!$M$8+Packages!$N$8+Packages!$O$8-1),"G",IF(C$4<=EOMONTH(Packages!$K$8,Packages!$L$8+Packages!$M$8+Packages!$N$8+Packages!$O$8+Packages!$P$8-1),"S","")))))) | D7: =IF(D$4<Packages!$K$8,"",IF(D$4<=EOMONTH(Packages!$K$8,Packages!$L$8-1),"D",IF(D$4<=EOMONTH(Packages!$K$8,Packages!$L$8+Packages!$M$8-1),"B",IF(D$4<=EOMONTH(Packages!$K$8,Packages!$L$8+Packages!$M$8+Packages!$N$8-1),"U",IF(D$4<=EOMONTH(Packages!$K$8,Packages!$L$8+Packages!$M$8+Packages!$N$8+Packages!$O$8-1),"G",IF(D$4<=EOMONTH(Packages!$K$8,Packages!$L$8+Packages!$M$8+Packages!$N$8+Packages!$O$8+Packages!$P$8-1),"S","")))))) -> D | E7: =IF(E$4<Packages!$K$8,"",IF(E$4<=EOMONTH(Packages!$K$8,Packages!$L$8-1),"D",IF(E$4<=EOMONTH(Packages!$K$8,Packages!$L$8+Packages!$M$8-1),"B",IF(E$4<=EOMONTH(Packages!$K$8,Packages!$L$8+Packages!$M$8+Packages!$N$8-1),"U",IF(E$4<=EOMONTH(Packages!$K$8,Packages!$L$8+Packages!$M$8+Packages!$N$8+Packages!$O$8-1),"G",IF(E$4<=EOMONTH(Packages!$K$8,Packages!$L$8+Packages!$M$8+Packages!$N$8+Packages!$O$8+Packages!$P$8-1),"S","")))))) -> D | F7: =IF(F$4<Packages!$K$8,"",IF(F$4<=EOMONTH(Packages!$K$8,Packages!$L$8-1),"D",IF(F$4<=EOMONTH(Packages!$K$8,Packages!$L$8+Packages!$M$8-1),"B",IF(F$4<=EOMONTH(Packages!$K$8,Packages!$L$8+Packages!$M$8+Packages!$N$8-1),"U",IF(F$4<=EOMONTH(Packages!$K$8,Packages!$L$8+Packages!$M$8+Packages!$N$8+Packages!$O$8-1),"G",IF(F$4<=EOMONTH(Packages!$K$8,Packages!$L$8+Packages!$M$8+Packages!$N$8+Packages!$O$8+Packages!$P$8-1),"S","")))))) -> B | G7: =IF(G$4<Packages!$K$8,"",IF(G$4<=EOMONTH(Packages!$K$8,Packages!$L$8-1),"D",IF(G$4<=EOMONTH(Packages!$K$8,Packages!$L$8+Packages!$M$8-1),"B",IF(G$4<=EOMONTH(Packages!$K$8,Packages!$L$8+Packages!$M$8+Packages!$N$8-1),"U",IF(G$4<=EOMONTH(Packages!$K$8,Packages!$L$8+Packages!$M$8+Packages!$N$8+Packages!$O$8-1),"G",IF(G$4<=EOMONTH(Packages!$K$8,Packages!$L$8+Packages!$M$8+Packages!$N$8+Packages!$O$8+Packages!$P$8-1),"S","")))))) -> B | H7: =IF(H$4<Packages!$K$8,"",IF(H$4<=EOMONTH(Packages!$K$8,Packages!$L$8-1),"D",IF(H$4<=EOMONTH(Packages!$K$8,Packages!$L$8+Packages!$M$8-1),"B",IF(H$4<=EOMONTH(Packages!$K$8,Packages!$L$8+Packages!$M$8+Packages!$N$8-1),"U",IF(H$4<=EOMONTH(Packages!$K$8,Packages!$L$8+Packages!$M$8+Packages!$N$8+Packages!$O$8-1),"G",IF(H$4<=EOMONTH(Packages!$K$8,Packages!$L$8+Packages!$M$8+Packages!$N$8+Packages!$O$8+Packages!$P$8-1),"S","")))))) -> B | I7: =IF(I$4<Packages!$K$8,"",IF(I$4<=EOMONTH(Packages!$K$8,Packages!$L$8-1),"D",IF(I$4<=EOMONTH(Packages!$K$8,Packages!$L$8+Packages!$M$8-1),"B",IF(I$4<=EOMONTH(Packages!$K$8,Packages!$L$8+Packages!$M$8+Packages!$N$8-1),"U",IF(I$4<=EOMONTH(Packages!$K$8,Packages!$L$8+Packages!$M$8+Packages!$N$8+Packages!$O$8-1),"G",IF(I$4<=EOMONTH(Packages!$K$8,Packages!$L$8+Packages!$M$8+Packages!$N$8+Packages!$O$8+Packages!$P$8-1),"S","")))))) -> B | J7: =IF(J$4<Packages!$K$8,"",IF(J$4<=EOMONTH(Packages!$K$8,Packages!$L$8-1),"D",IF(J$4<=EOMONTH(Packages!$K$8,Packages!$L$8+Packages!$M$8-1),"B",IF(J$4<=EOMONTH(Packages!$K$8,Packages!$L$8+Packages!$M$8+Packages!$N$8-1),"U",IF(J$4<=EOMONTH(Packages!$K$8,Packages!$L$8+Packages!$M$8+Packages!$N$8+Packages!$O$8-1),"G",IF(J$4<=EOMONTH(Packages!$K$8,Packages!$L$8+Packages!$M$8+Packages!$N$8+Packages!$O$8+Packages!$P$8-1),"S","")))))) -> B | ... AO7: =IF(AO$4<Packages!$K$8,"",IF(AO$4<=EOMONTH(Packages!$K$8,Packages!$L$8-1),"D",IF(AO$4<=EOMONTH(Packages!$K$8,Packages!$L$8+Packages!$M$8-1),"B",IF(AO$4<=EOMONTH(Packages!$K$8,Packages!$L$8+Packages!$M$8+Packages!$N$8-1),"U",IF(AO$4<=EOMONTH(Packages!$K$8,Packages!$L$8+Packages!$M$8+Packages!$N$8+Packages!$O$8-1),"G",IF(AO$4<=EOMONTH(Packages!$K$8,Packages!$L$8+Packages!$M$8+Packages!$N$8+Packages!$O$8+Packages!$P$8-1),"S",""))))))
A8: =Packages!A9 -> WP4 | B8: =Packages!B9 -> Enforcement & field metrology: Mobile Court, Surveillance, Verification, Tank Calibration, Metrology Licence, Storage Tank Calibration | C8: =IF(C$4<Packages!$K$9,"",IF(C$4<=EOMONTH(Packages!$K$9,Packages!$L$9-1),"D",IF(C$4<=EOMONTH(Packages!$K$9,Packages!$L$9+Packages!$M$9-1),"B",IF(C$4<=EOMONTH(Packages!$K$9,Packages!$L$9+Packages!$M$9+Packages!$N$9-1),"U",IF(C$4<=EOMONTH(Packages!$K$9,Packages!$L$9+Packages!$M$9+Packages!$N$9+Packages!$O$9-1),"G",IF(C$4<=EOMONTH(Packages!$K$9,Packages!$L$9+Packages!$M$9+Packages!$N$9+Packages!$O$9+Packages!$P$9-1),"S","")))))) | D8: =IF(D$4<Packages!$K$9,"",IF(D$4<=EOMONTH(Packages!$K$9,Packages!$L$9-1),"D",IF(D$4<=EOMONTH(Packages!$K$9,Packages!$L$9+Packages!$M$9-1),"B",IF(D$4<=EOMONTH(Packages!$K$9,Packages!$L$9+Packages!$M$9+Packages!$N$9-1),"U",IF(D$4<=EOMONTH(Packages!$K$9,Packages!$L$9+Packages!$M$9+Packages!$N$9+Packages!$O$9-1),"G",IF(D$4<=EOMONTH(Packages!$K$9,Packages!$L$9+Packages!$M$9+Packages!$N$9+Packages!$O$9+Packages!$P$9-1),"S","")))))) | E8: =IF(E$4<Packages!$K$9,"",IF(E$4<=EOMONTH(Packages!$K$9,Packages!$L$9-1),"D",IF(E$4<=EOMONTH(Packages!$K$9,Packages!$L$9+Packages!$M$9-1),"B",IF(E$4<=EOMONTH(Packages!$K$9,Packages!$L$9+Packages!$M$9+Packages!$N$9-1),"U",IF(E$4<=EOMONTH(Packages!$K$9,Packages!$L$9+Packages!$M$9+Packages!$N$9+Packages!$O$9-1),"G",IF(E$4<=EOMONTH(Packages!$K$9,Packages!$L$9+Packages!$M$9+Packages!$N$9+Packages!$O$9+Packages!$P$9-1),"S","")))))) | F8: =IF(F$4<Packages!$K$9,"",IF(F$4<=EOMONTH(Packages!$K$9,Packages!$L$9-1),"D",IF(F$4<=EOMONTH(Packages!$K$9,Packages!$L$9+Packages!$M$9-1),"B",IF(F$4<=EOMONTH(Packages!$K$9,Packages!$L$9+Packages!$M$9+Packages!$N$9-1),"U",IF(F$4<=EOMONTH(Packages!$K$9,Packages!$L$9+Packages!$M$9+Packages!$N$9+Packages!$O$9-1),"G",IF(F$4<=EOMONTH(Packages!$K$9,Packages!$L$9+Packages!$M$9+Packages!$N$9+Packages!$O$9+Packages!$P$9-1),"S","")))))) | G8: =IF(G$4<Packages!$K$9,"",IF(G$4<=EOMONTH(Packages!$K$9,Packages!$L$9-1),"D",IF(G$4<=EOMONTH(Packages!$K$9,Packages!$L$9+Packages!$M$9-1),"B",IF(G$4<=EOMONTH(Packages!$K$9,Packages!$L$9+Packages!$M$9+Packages!$N$9-1),"U",IF(G$4<=EOMONTH(Packages!$K$9,Packages!$L$9+Packages!$M$9+Packages!$N$9+Packages!$O$9-1),"G",IF(G$4<=EOMONTH(Packages!$K$9,Packages!$L$9+Packages!$M$9+Packages!$N$9+Packages!$O$9+Packages!$P$9-1),"S","")))))) | H8: =IF(H$4<Packages!$K$9,"",IF(H$4<=EOMONTH(Packages!$K$9,Packages!$L$9-1),"D",IF(H$4<=EOMONTH(Packages!$K$9,Packages!$L$9+Packages!$M$9-1),"B",IF(H$4<=EOMONTH(Packages!$K$9,Packages!$L$9+Packages!$M$9+Packages!$N$9-1),"U",IF(H$4<=EOMONTH(Packages!$K$9,Packages!$L$9+Packages!$M$9+Packages!$N$9+Packages!$O$9-1),"G",IF(H$4<=EOMONTH(Packages!$K$9,Packages!$L$9+Packages!$M$9+Packages!$N$9+Packages!$O$9+Packages!$P$9-1),"S","")))))) | I8: =IF(I$4<Packages!$K$9,"",IF(I$4<=EOMONTH(Packages!$K$9,Packages!$L$9-1),"D",IF(I$4<=EOMONTH(Packages!$K$9,Packages!$L$9+Packages!$M$9-1),"B",IF(I$4<=EOMONTH(Packages!$K$9,Packages!$L$9+Packages!$M$9+Packages!$N$9-1),"U",IF(I$4<=EOMONTH(Packages!$K$9,Packages!$L$9+Packages!$M$9+Packages!$N$9+Packages!$O$9-1),"G",IF(I$4<=EOMONTH(Packages!$K$9,Packages!$L$9+Packages!$M$9+Packages!$N$9+Packages!$O$9+Packages!$P$9-1),"S","")))))) | J8: =IF(J$4<Packages!$K$9,"",IF(J$4<=EOMONTH(Packages!$K$9,Packages!$L$9-1),"D",IF(J$4<=EOMONTH(Packages!$K$9,Packages!$L$9+Packages!$M$9-1),"B",IF(J$4<=EOMONTH(Packages!$K$9,Packages!$L$9+Packages!$M$9+Packages!$N$9-1),"U",IF(J$4<=EOMONTH(Packages!$K$9,Packages!$L$9+Packages!$M$9+Packages!$N$9+Packages!$O$9-1),"G",IF(J$4<=EOMONTH(Packages!$K$9,Packages!$L$9+Packages!$M$9+Packages!$N$9+Packages!$O$9+Packages!$P$9-1),"S","")))))) | ... AO8: =IF(AO$4<Packages!$K$9,"",IF(AO$4<=EOMONTH(Packages!$K$9,Packages!$L$9-1),"D",IF(AO$4<=EOMONTH(Packages!$K$9,Packages!$L$9+Packages!$M$9-1),"B",IF(AO$4<=EOMONTH(Packages!$K$9,Packages!$L$9+Packages!$M$9+Packages!$N$9-1),"U",IF(AO$4<=EOMONTH(Packages!$K$9,Packages!$L$9+Packages!$M$9+Packages!$N$9+Packages!$O$9-1),"G",IF(AO$4<=EOMONTH(Packages!$K$9,Packages!$L$9+Packages!$M$9+Packages!$N$9+Packages!$O$9+Packages!$P$9-1),"S",""))))))
A9: =Packages!A10 -> WP5 | B9: =Packages!B10 -> MSC services (issue, renewal, scope inclusion) | C9: =IF(C$4<Packages!$K$10,"",IF(C$4<=EOMONTH(Packages!$K$10,Packages!$L$10-1),"D",IF(C$4<=EOMONTH(Packages!$K$10,Packages!$L$10+Packages!$M$10-1),"B",IF(C$4<=EOMONTH(Packages!$K$10,Packages!$L$10+Packages!$M$10+Packages!$N$10-1),"U",IF(C$4<=EOMONTH(Packages!$K$10,Packages!$L$10+Packages!$M$10+Packages!$N$10+Packages!$O$10-1),"G",IF(C$4<=EOMONTH(Packages!$K$10,Packages!$L$10+Packages!$M$10+Packages!$N$10+Packages!$O$10+Packages!$P$10-1),"S","")))))) | D9: =IF(D$4<Packages!$K$10,"",IF(D$4<=EOMONTH(Packages!$K$10,Packages!$L$10-1),"D",IF(D$4<=EOMONTH(Packages!$K$10,Packages!$L$10+Packages!$M$10-1),"B",IF(D$4<=EOMONTH(Packages!$K$10,Packages!$L$10+Packages!$M$10+Packages!$N$10-1),"U",IF(D$4<=EOMONTH(Packages!$K$10,Packages!$L$10+Packages!$M$10+Packages!$N$10+Packages!$O$10-1),"G",IF(D$4<=EOMONTH(Packages!$K$10,Packages!$L$10+Packages!$M$10+Packages!$N$10+Packages!$O$10+Packages!$P$10-1),"S","")))))) | E9: =IF(E$4<Packages!$K$10,"",IF(E$4<=EOMONTH(Packages!$K$10,Packages!$L$10-1),"D",IF(E$4<=EOMONTH(Packages!$K$10,Packages!$L$10+Packages!$M$10-1),"B",IF(E$4<=EOMONTH(Packages!$K$10,Packages!$L$10+Packages!$M$10+Packages!$N$10-1),"U",IF(E$4<=EOMONTH(Packages!$K$10,Packages!$L$10+Packages!$M$10+Packages!$N$10+Packages!$O$10-1),"G",IF(E$4<=EOMONTH(Packages!$K$10,Packages!$L$10+Packages!$M$10+Packages!$N$10+Packages!$O$10+Packages!$P$10-1),"S","")))))) | F9: =IF(F$4<Packages!$K$10,"",IF(F$4<=EOMONTH(Packages!$K$10,Packages!$L$10-1),"D",IF(F$4<=EOMONTH(Packages!$K$10,Packages!$L$10+Packages!$M$10-1),"B",IF(F$4<=EOMONTH(Packages!$K$10,Packages!$L$10+Packages!$M$10+Packages!$N$10-1),"U",IF(F$4<=EOMONTH(Packages!$K$10,Packages!$L$10+Packages!$M$10+Packages!$N$10+Packages!$O$10-1),"G",IF(F$4<=EOMONTH(Packages!$K$10,Packages!$L$10+Packages!$M$10+Packages!$N$10+Packages!$O$10+Packages!$P$10-1),"S","")))))) | G9: =IF(G$4<Packages!$K$10,"",IF(G$4<=EOMONTH(Packages!$K$10,Packages!$L$10-1),"D",IF(G$4<=EOMONTH(Packages!$K$10,Packages!$L$10+Packages!$M$10-1),"B",IF(G$4<=EOMONTH(Packages!$K$10,Packages!$L$10+Packages!$M$10+Packages!$N$10-1),"U",IF(G$4<=EOMONTH(Packages!$K$10,Packages!$L$10+Packages!$M$10+Packages!$N$10+Packages!$O$10-1),"G",IF(G$4<=EOMONTH(Packages!$K$10,Packages!$L$10+Packages!$M$10+Packages!$N$10+Packages!$O$10+Packages!$P$10-1),"S","")))))) | H9: =IF(H$4<Packages!$K$10,"",IF(H$4<=EOMONTH(Packages!$K$10,Packages!$L$10-1),"D",IF(H$4<=EOMONTH(Packages!$K$10,Packages!$L$10+Packages!$M$10-1),"B",IF(H$4<=EOMONTH(Packages!$K$10,Packages!$L$10+Packages!$M$10+Packages!$N$10-1),"U",IF(H$4<=EOMONTH(Packages!$K$10,Packages!$L$10+Packages!$M$10+Packages!$N$10+Packages!$O$10-1),"G",IF(H$4<=EOMONTH(Packages!$K$10,Packages!$L$10+Packages!$M$10+Packages!$N$10+Packages!$O$10+Packages!$P$10-1),"S","")))))) | I9: =IF(I$4<Packages!$K$10,"",IF(I$4<=EOMONTH(Packages!$K$10,Packages!$L$10-1),"D",IF(I$4<=EOMONTH(Packages!$K$10,Packages!$L$10+Packages!$M$10-1),"B",IF(I$4<=EOMONTH(Packages!$K$10,Packages!$L$10+Packages!$M$10+Packages!$N$10-1),"U",IF(I$4<=EOMONTH(Packages!$K$10,Packages!$L$10+Packages!$M$10+Packages!$N$10+Packages!$O$10-1),"G",IF(I$4<=EOMONTH(Packages!$K$10,Packages!$L$10+Packages!$M$10+Packages!$N$10+Packages!$O$10+Packages!$P$10-1),"S","")))))) | J9: =IF(J$4<Packages!$K$10,"",IF(J$4<=EOMONTH(Packages!$K$10,Packages!$L$10-1),"D",IF(J$4<=EOMONTH(Packages!$K$10,Packages!$L$10+Packages!$M$10-1),"B",IF(J$4<=EOMONTH(Packages!$K$10,Packages!$L$10+Packages!$M$10+Packages!$N$10-1),"U",IF(J$4<=EOMONTH(Packages!$K$10,Packages!$L$10+Packages!$M$10+Packages!$N$10+Packages!$O$10-1),"G",IF(J$4<=EOMONTH(Packages!$K$10,Packages!$L$10+Packages!$M$10+Packages!$N$10+Packages!$O$10+Packages!$P$10-1),"S","")))))) | ... AO9: =IF(AO$4<Packages!$K$10,"",IF(AO$4<=EOMONTH(Packages!$K$10,Packages!$L$10-1),"D",IF(AO$4<=EOMONTH(Packages!$K$10,Packages!$L$10+Packages!$M$10-1),"B",IF(AO$4<=EOMONTH(Packages!$K$10,Packages!$L$10+Packages!$M$10+Packages!$N$10-1),"U",IF(AO$4<=EOMONTH(Packages!$K$10,Packages!$L$10+Packages!$M$10+Packages!$N$10+Packages!$O$10-1),"G",IF(AO$4<=EOMONTH(Packages!$K$10,Packages!$L$10+Packages!$M$10+Packages!$N$10+Packages!$O$10+Packages!$P$10-1),"S",""))))))
A10: =Packages!A11 -> WP6 | B10: =Packages!B11 -> Halal certification, LPG / Fuel station registration, Case Management | C10: =IF(C$4<Packages!$K$11,"",IF(C$4<=EOMONTH(Packages!$K$11,Packages!$L$11-1),"D",IF(C$4<=EOMONTH(Packages!$K$11,Packages!$L$11+Packages!$M$11-1),"B",IF(C$4<=EOMONTH(Packages!$K$11,Packages!$L$11+Packages!$M$11+Packages!$N$11-1),"U",IF(C$4<=EOMONTH(Packages!$K$11,Packages!$L$11+Packages!$M$11+Packages!$N$11+Packages!$O$11-1),"G",IF(C$4<=EOMONTH(Packages!$K$11,Packages!$L$11+Packages!$M$11+Packages!$N$11+Packages!$O$11+Packages!$P$11-1),"S","")))))) | D10: =IF(D$4<Packages!$K$11,"",IF(D$4<=EOMONTH(Packages!$K$11,Packages!$L$11-1),"D",IF(D$4<=EOMONTH(Packages!$K$11,Packages!$L$11+Packages!$M$11-1),"B",IF(D$4<=EOMONTH(Packages!$K$11,Packages!$L$11+Packages!$M$11+Packages!$N$11-1),"U",IF(D$4<=EOMONTH(Packages!$K$11,Packages!$L$11+Packages!$M$11+Packages!$N$11+Packages!$O$11-1),"G",IF(D$4<=EOMONTH(Packages!$K$11,Packages!$L$11+Packages!$M$11+Packages!$N$11+Packages!$O$11+Packages!$P$11-1),"S","")))))) | E10: =IF(E$4<Packages!$K$11,"",IF(E$4<=EOMONTH(Packages!$K$11,Packages!$L$11-1),"D",IF(E$4<=EOMONTH(Packages!$K$11,Packages!$L$11+Packages!$M$11-1),"B",IF(E$4<=EOMONTH(Packages!$K$11,Packages!$L$11+Packages!$M$11+Packages!$N$11-1),"U",IF(E$4<=EOMONTH(Packages!$K$11,Packages!$L$11+Packages!$M$11+Packages!$N$11+Packages!$O$11-1),"G",IF(E$4<=EOMONTH(Packages!$K$11,Packages!$L$11+Packages!$M$11+Packages!$N$11+Packages!$O$11+Packages!$P$11-1),"S","")))))) | F10: =IF(F$4<Packages!$K$11,"",IF(F$4<=EOMONTH(Packages!$K$11,Packages!$L$11-1),"D",IF(F$4<=EOMONTH(Packages!$K$11,Packages!$L$11+Packages!$M$11-1),"B",IF(F$4<=EOMONTH(Packages!$K$11,Packages!$L$11+Packages!$M$11+Packages!$N$11-1),"U",IF(F$4<=EOMONTH(Packages!$K$11,Packages!$L$11+Packages!$M$11+Packages!$N$11+Packages!$O$11-1),"G",IF(F$4<=EOMONTH(Packages!$K$11,Packages!$L$11+Packages!$M$11+Packages!$N$11+Packages!$O$11+Packages!$P$11-1),"S","")))))) | G10: =IF(G$4<Packages!$K$11,"",IF(G$4<=EOMONTH(Packages!$K$11,Packages!$L$11-1),"D",IF(G$4<=EOMONTH(Packages!$K$11,Packages!$L$11+Packages!$M$11-1),"B",IF(G$4<=EOMONTH(Packages!$K$11,Packages!$L$11+Packages!$M$11+Packages!$N$11-1),"U",IF(G$4<=EOMONTH(Packages!$K$11,Packages!$L$11+Packages!$M$11+Packages!$N$11+Packages!$O$11-1),"G",IF(G$4<=EOMONTH(Packages!$K$11,Packages!$L$11+Packages!$M$11+Packages!$N$11+Packages!$O$11+Packages!$P$11-1),"S","")))))) | H10: =IF(H$4<Packages!$K$11,"",IF(H$4<=EOMONTH(Packages!$K$11,Packages!$L$11-1),"D",IF(H$4<=EOMONTH(Packages!$K$11,Packages!$L$11+Packages!$M$11-1),"B",IF(H$4<=EOMONTH(Packages!$K$11,Packages!$L$11+Packages!$M$11+Packages!$N$11-1),"U",IF(H$4<=EOMONTH(Packages!$K$11,Packages!$L$11+Packages!$M$11+Packages!$N$11+Packages!$O$11-1),"G",IF(H$4<=EOMONTH(Packages!$K$11,Packages!$L$11+Packages!$M$11+Packages!$N$11+Packages!$O$11+Packages!$P$11-1),"S","")))))) | I10: =IF(I$4<Packages!$K$11,"",IF(I$4<=EOMONTH(Packages!$K$11,Packages!$L$11-1),"D",IF(I$4<=EOMONTH(Packages!$K$11,Packages!$L$11+Packages!$M$11-1),"B",IF(I$4<=EOMONTH(Packages!$K$11,Packages!$L$11+Packages!$M$11+Packages!$N$11-1),"U",IF(I$4<=EOMONTH(Packages!$K$11,Packages!$L$11+Packages!$M$11+Packages!$N$11+Packages!$O$11-1),"G",IF(I$4<=EOMONTH(Packages!$K$11,Packages!$L$11+Packages!$M$11+Packages!$N$11+Packages!$O$11+Packages!$P$11-1),"S","")))))) | J10: =IF(J$4<Packages!$K$11,"",IF(J$4<=EOMONTH(Packages!$K$11,Packages!$L$11-1),"D",IF(J$4<=EOMONTH(Packages!$K$11,Packages!$L$11+Packages!$M$11-1),"B",IF(J$4<=EOMONTH(Packages!$K$11,Packages!$L$11+Packages!$M$11+Packages!$N$11-1),"U",IF(J$4<=EOMONTH(Packages!$K$11,Packages!$L$11+Packages!$M$11+Packages!$N$11+Packages!$O$11-1),"G",IF(J$4<=EOMONTH(Packages!$K$11,Packages!$L$11+Packages!$M$11+Packages!$N$11+Packages!$O$11+Packages!$P$11-1),"S","")))))) | ... AO10: =IF(AO$4<Packages!$K$11,"",IF(AO$4<=EOMONTH(Packages!$K$11,Packages!$L$11-1),"D",IF(AO$4<=EOMONTH(Packages!$K$11,Packages!$L$11+Packages!$M$11-1),"B",IF(AO$4<=EOMONTH(Packages!$K$11,Packages!$L$11+Packages!$M$11+Packages!$N$11-1),"U",IF(AO$4<=EOMONTH(Packages!$K$11,Packages!$L$11+Packages!$M$11+Packages!$N$11+Packages!$O$11-1),"G",IF(AO$4<=EOMONTH(Packages!$K$11,Packages!$L$11+Packages!$M$11+Packages!$N$11+Packages!$O$11+Packages!$P$11-1),"S",""))))))
A11: =Packages!A12 -> WP7 | B11: =Packages!B12 -> I&S Metrology Calibration (NML), Building measurement, BSW API integration, Importer/Exporter certificates* | C11: =IF(C$4<Packages!$K$12,"",IF(C$4<=EOMONTH(Packages!$K$12,Packages!$L$12-1),"D",IF(C$4<=EOMONTH(Packages!$K$12,Packages!$L$12+Packages!$M$12-1),"B",IF(C$4<=EOMONTH(Packages!$K$12,Packages!$L$12+Packages!$M$12+Packages!$N$12-1),"U",IF(C$4<=EOMONTH(Packages!$K$12,Packages!$L$12+Packages!$M$12+Packages!$N$12+Packages!$O$12-1),"G",IF(C$4<=EOMONTH(Packages!$K$12,Packages!$L$12+Packages!$M$12+Packages!$N$12+Packages!$O$12+Packages!$P$12-1),"S","")))))) | D11: =IF(D$4<Packages!$K$12,"",IF(D$4<=EOMONTH(Packages!$K$12,Packages!$L$12-1),"D",IF(D$4<=EOMONTH(Packages!$K$12,Packages!$L$12+Packages!$M$12-1),"B",IF(D$4<=EOMONTH(Packages!$K$12,Packages!$L$12+Packages!$M$12+Packages!$N$12-1),"U",IF(D$4<=EOMONTH(Packages!$K$12,Packages!$L$12+Packages!$M$12+Packages!$N$12+Packages!$O$12-1),"G",IF(D$4<=EOMONTH(Packages!$K$12,Packages!$L$12+Packages!$M$12+Packages!$N$12+Packages!$O$12+Packages!$P$12-1),"S","")))))) | E11: =IF(E$4<Packages!$K$12,"",IF(E$4<=EOMONTH(Packages!$K$12,Packages!$L$12-1),"D",IF(E$4<=EOMONTH(Packages!$K$12,Packages!$L$12+Packages!$M$12-1),"B",IF(E$4<=EOMONTH(Packages!$K$12,Packages!$L$12+Packages!$M$12+Packages!$N$12-1),"U",IF(E$4<=EOMONTH(Packages!$K$12,Packages!$L$12+Packages!$M$12+Packages!$N$12+Packages!$O$12-1),"G",IF(E$4<=EOMONTH(Packages!$K$12,Packages!$L$12+Packages!$M$12+Packages!$N$12+Packages!$O$12+Packages!$P$12-1),"S","")))))) | F11: =IF(F$4<Packages!$K$12,"",IF(F$4<=EOMONTH(Packages!$K$12,Packages!$L$12-1),"D",IF(F$4<=EOMONTH(Packages!$K$12,Packages!$L$12+Packages!$M$12-1),"B",IF(F$4<=EOMONTH(Packages!$K$12,Packages!$L$12+Packages!$M$12+Packages!$N$12-1),"U",IF(F$4<=EOMONTH(Packages!$K$12,Packages!$L$12+Packages!$M$12+Packages!$N$12+Packages!$O$12-1),"G",IF(F$4<=EOMONTH(Packages!$K$12,Packages!$L$12+Packages!$M$12+Packages!$N$12+Packages!$O$12+Packages!$P$12-1),"S","")))))) | G11: =IF(G$4<Packages!$K$12,"",IF(G$4<=EOMONTH(Packages!$K$12,Packages!$L$12-1),"D",IF(G$4<=EOMONTH(Packages!$K$12,Packages!$L$12+Packages!$M$12-1),"B",IF(G$4<=EOMONTH(Packages!$K$12,Packages!$L$12+Packages!$M$12+Packages!$N$12-1),"U",IF(G$4<=EOMONTH(Packages!$K$12,Packages!$L$12+Packages!$M$12+Packages!$N$12+Packages!$O$12-1),"G",IF(G$4<=EOMONTH(Packages!$K$12,Packages!$L$12+Packages!$M$12+Packages!$N$12+Packages!$O$12+Packages!$P$12-1),"S","")))))) | H11: =IF(H$4<Packages!$K$12,"",IF(H$4<=EOMONTH(Packages!$K$12,Packages!$L$12-1),"D",IF(H$4<=EOMONTH(Packages!$K$12,Packages!$L$12+Packages!$M$12-1),"B",IF(H$4<=EOMONTH(Packages!$K$12,Packages!$L$12+Packages!$M$12+Packages!$N$12-1),"U",IF(H$4<=EOMONTH(Packages!$K$12,Packages!$L$12+Packages!$M$12+Packages!$N$12+Packages!$O$12-1),"G",IF(H$4<=EOMONTH(Packages!$K$12,Packages!$L$12+Packages!$M$12+Packages!$N$12+Packages!$O$12+Packages!$P$12-1),"S","")))))) | I11: =IF(I$4<Packages!$K$12,"",IF(I$4<=EOMONTH(Packages!$K$12,Packages!$L$12-1),"D",IF(I$4<=EOMONTH(Packages!$K$12,Packages!$L$12+Packages!$M$12-1),"B",IF(I$4<=EOMONTH(Packages!$K$12,Packages!$L$12+Packages!$M$12+Packages!$N$12-1),"U",IF(I$4<=EOMONTH(Packages!$K$12,Packages!$L$12+Packages!$M$12+Packages!$N$12+Packages!$O$12-1),"G",IF(I$4<=EOMONTH(Packages!$K$12,Packages!$L$12+Packages!$M$12+Packages!$N$12+Packages!$O$12+Packages!$P$12-1),"S","")))))) | J11: =IF(J$4<Packages!$K$12,"",IF(J$4<=EOMONTH(Packages!$K$12,Packages!$L$12-1),"D",IF(J$4<=EOMONTH(Packages!$K$12,Packages!$L$12+Packages!$M$12-1),"B",IF(J$4<=EOMONTH(Packages!$K$12,Packages!$L$12+Packages!$M$12+Packages!$N$12-1),"U",IF(J$4<=EOMONTH(Packages!$K$12,Packages!$L$12+Packages!$M$12+Packages!$N$12+Packages!$O$12-1),"G",IF(J$4<=EOMONTH(Packages!$K$12,Packages!$L$12+Packages!$M$12+Packages!$N$12+Packages!$O$12+Packages!$P$12-1),"S","")))))) | ... AO11: =IF(AO$4<Packages!$K$12,"",IF(AO$4<=EOMONTH(Packages!$K$12,Packages!$L$12-1),"D",IF(AO$4<=EOMONTH(Packages!$K$12,Packages!$L$12+Packages!$M$12-1),"B",IF(AO$4<=EOMONTH(Packages!$K$12,Packages!$L$12+Packages!$M$12+Packages!$N$12-1),"U",IF(AO$4<=EOMONTH(Packages!$K$12,Packages!$L$12+Packages!$M$12+Packages!$N$12+Packages!$O$12-1),"G",IF(AO$4<=EOMONTH(Packages!$K$12,Packages!$L$12+Packages!$M$12+Packages!$N$12+Packages!$O$12+Packages!$P$12-1),"S","")))))) -> S
B12: Packages in parallel (design/build/UAT/go-live) | C12: =COUNTIF(C5:C11,"D")+COUNTIF(C5:C11,"B")+COUNTIF(C5:C11,"U")+COUNTIF(C5:C11,"G") -> 1 | D12: =COUNTIF(D5:D11,"D")+COUNTIF(D5:D11,"B")+COUNTIF(D5:D11,"U")+COUNTIF(D5:D11,"G") -> 2 | E12: =COUNTIF(E5:E11,"D")+COUNTIF(E5:E11,"B")+COUNTIF(E5:E11,"U")+COUNTIF(E5:E11,"G") -> 3 | F12: =COUNTIF(F5:F11,"D")+COUNTIF(F5:F11,"B")+COUNTIF(F5:F11,"U")+COUNTIF(F5:F11,"G") -> 3 | G12: =COUNTIF(G5:G11,"D")+COUNTIF(G5:G11,"B")+COUNTIF(G5:G11,"U")+COUNTIF(G5:G11,"G") -> 3 | H12: =COUNTIF(H5:H11,"D")+COUNTIF(H5:H11,"B")+COUNTIF(H5:H11,"U")+COUNTIF(H5:H11,"G") -> 3 | I12: =COUNTIF(I5:I11,"D")+COUNTIF(I5:I11,"B")+COUNTIF(I5:I11,"U")+COUNTIF(I5:I11,"G") -> 2 | J12: =COUNTIF(J5:J11,"D")+COUNTIF(J5:J11,"B")+COUNTIF(J5:J11,"U")+COUNTIF(J5:J11,"G") -> 2 | ... AO12: =COUNTIF(AO5:AO11,"D")+COUNTIF(AO5:AO11,"B")+COUNTIF(AO5:AO11,"U")+COUNTIF(AO5:AO11,"G") -> 0

Sheet Notes
A1: Method, assumptions and points to confirm
A3: Method
A4: 1 | B4: The rollout total of BDT 11,16,65,000 (Financial Proposal V4, p.4) is kept unchanged. Only its split changes: from 'per live service per month' to 'per accepted deliverable'.
A5: 2 | B5: BDT 16,25,000 for Aug–Dec 2026 is kept as a separate O&M package (WP0) because it pays for running the 5 live services, not new work. The remaining BDT 11,00,40,000 is allocated by work volume.
A6: 3 | B6: Work volume = feature count per service from OrangeBD's own deck (BSTI 2.0.pptx, slides 14–46; 440 modules / 2,168 features in total). Where serial.docx splits one deck service into sub-types (Verification, Tank, Storage Tank, Surveillance), the parent's features are split equally.
A7: 4 | B7: Features are weighted by work type: New = 1.0, Variant (renewal / brand / scope inclusion / re-certification) = 0.5, Live in v1 (re-platforming + migration) = 0.5. Session 1 found the variant SRS sections 85–99% identical. Factors are inputs; set all to 1.0 for a pure feature-count split.
A8: 5 | B8: Packages follow serial.docx priority and are cut so that each approval, including 15% VAT, stays under BDT 2 crore. Change a row's package code on 'Work Volume' to move it; the cap check flags any breach.
A9: 6 | B9: Payments are tied to accepted milestones (20% design sign-off / 30% UAT / 40% go-live / 10% after stabilisation), replacing monthly per-service billing. Each package price includes support of its services until maintenance starts in Jan 2030.
A10: 7 | B10: Maintenance 2030–31 (BDT 7,52,40,000) is unchanged. Because a full year (3.76 crore) exceeds the cap, it is approved in quarterly tranches of BDT 94,05,000.
A11: Development time limits
A12: 8 | B12: Core services first: Accounts (WP1), CM (WP2), labs and PCR (WP3) go live by 30 Nov 2027, so they are fully running in December 2027 (user instruction). WP3 starts first (Feb 2027, 10 months) because CM scope, Halal and MSC all depend on lab testing; CM starts Mar 2027 (9 months) and integrates with the lab module. WP1–WP3 run in parallel Mar–Jun 2027.
A13: 9 | B13: Approvals for WP1, WP3 and WP2 are needed one per month (by 30 Nov 2026, 31 Dec 2026 and 31 Jan 2027), each under 2 crore. WP4–WP7 follow from Apr 2028, staggered 3–6 months apart; final go-live 31 Dec 2029, the same end date as the proposal.
A14: 10 | B14: Suggested contract clause (to confirm with the procurement / legal cell): liquidated damages for delay past the go-live deadline, e.g. 0.05% of the package value per day, capped at 10% (PPR and standard tender document terms apply).
A15: BSTI estimates (yellow cells): no scope in the SRS or deck
A16: 11 | B16: Common platform (unified portal and SSO, 23-office organogram, workflow / fee-payment / certificate-QR engines, v1 data migration): 60 features.
A17: 12 | B17: BDS (Standards) sale re-platforming: 40 features. It is live in v1, has no SRS section, and takes service 23's slot.
A18: 13 | B18: Suspension / cancellation / withdrawal of all certificates and licences (serial.docx footnote): 30 features, built once in WP2 and reused.
A19: 14 | B19: MSC Scope Inclusion: 50 features. BSW API integration: 30 features.
A20: Points to confirm
A21: 15 | B21: Registered Importer/Exporter (new and renewal) are marked * in serial.docx. They are included as the last priority (WP7). Set 'Include?' to N on 'Work Volume' to drop them; the freed amount is spread over the rest automatically.
A22: 16 | B22: Metrology dealer licence (earlier proposed as replacement for service 22) is not in serial.docx and is not costed here.
A23: 17 | B23: VAT/tax rate for the approval check (15% assumed), and whether the 2-crore limit is measured including VAT.
A24: 18 | B24: Feature counts are OrangeBD's own; they measure documented scope, not effort. An independent effort estimate would firm up the split.
